Workbook

Sheet Identification
A1: No enregistrement | B1: Societe | C1: Pays | D1: Branche | E1: Directeur general | F1: Date de creation | G1: Capital social (F CFA) | H1: Cadres | I1: Maitrise | J1: Employes | K1: Annee N
A2: 1 | B2: ATLANTIQUE ASSURANCE BENIN VIE | C2: BENIN | D2: Vie | E2: Corinne GBENOU FOURN | F2: 34662 | G2: 3299350000 | H2: 9 | I2: 6 | J2: 2 | K2: 2023
A3: 2 | B3: CIF ASSURANCES VIE | C3: BENIN | D3: Vie | E3: Félix Edouard LADEKAN | F3: 41261 | G3: 1249280000 | H3: 11 | I3: 2 | J3: 2 | K3: 2023
A4: 3 | B4: L'AFRICAINE VIE BENIN | C4: BENIN | D4: Vie | E4: Hervé TCHIAKPE | F4: 38821 | G4: 3000000000 | H4: 10 | I4: 17 | J4: 2 | K4: 2023
A5: 4 | B5: NOUVELLE SOCIETE INTERAFRICAINE D'ASSURANCES VIE | C5: BENIN | D5: Vie | E5: DOSSOU FREJUS LIDWIN | F5: 38457 | G5: 3000000000 | H5: 14 | I5: 9 | J5: 2 | K5: 2023
A6: 5 | B6: SANLAM ASSURANCE VIE | C6: BENIN | D6: Vie | E6: Mariam NASSIROU | F6: 35230 | G6: 3000000000 | H6: 16 | I6: 49 | J6: 0 | K6: 2023
A7: 6 | B7: SUNU ASSURANCES VIE BENIN | C7: BENIN | D7: Vie | E7: Souleymane Wassila FAYE | F7: 34655 | G7: 3000000000 | H7: 37 | I7: 6 | J7: 1 | K7: 2023
A8: 7 | B8: ATLANTIQUE ASSURANCES BENIN IARDT | C8: BENIN | D8: Non-vie | E8: AYIVI-ELEGBEDE Florence | F8: 42459 | G8: 5000000000 | H8: 21 | I8: 23 | J8: 4 | K8: 2023
A9: 8 | B9: L'AFRICAINE DES ASSURANCES | C9: BENIN | D9: Non-vie | E9: Kenneth ELEGBEDE | F9: 35739 | G9: 4493470000 | H9: 29 | I9: 48 | J9: 7 | K9: 2023
A10: 9 | B10: LA GENERALE DES ASSURANCES | C10: BENIN | D10: Non-vie | E10: Gaston Arnaud de SOUZA | F10: 36280 | G10: 3000000000 | H10: 7 | I10: 9 | J10: 9 | K10: 2023
A11: 10 | B11: NOBILA ASSURANCES SA | C11: BENIN | D11: Non-vie | E11: André A. AZIBLI | F11: 38630 | G11: 3000000000 | H11: 9 | I11: 8 | J11: 11 | K11: 2023
A12: 11 | B12: NOUVELLE SOCIETE INTERAFRICAINE D'ASSURANCES | C12: BENIN | D12: Non-vie | E12: AGBOTA Fabrice | F12: 35796 | G12: 4800000000 | H12: 27 | I12: 25 | J12: 4 | K12: 2023
A13: 12 | B13: SANLAM ASSURANCE | C13: BENIN | D13: Non-vie | E13: Edmond DOSSOU | F13: 40420 | G13: 3000000000 | H13: 12 | I13: 22 | J13: 2 | K13: 2023
... A48: 47 | B48: ALLIANZ CÔTE D'IVOIRE ASSURANCES | C48: COTE D'IVOIRE | D48: Non-vie | E48: Mamadou G. K. KONE | F48: 27760 | G48: 3000000000 | H48: 55 | I48: 49 | J48: 2 | K48: 2023
A49: 48 | B49: AMSA ASSURANCES | C49: COTE D'IVOIRE | D49: Non-vie | E49: Yatassaye SAMBA | F49: En 1972 | G49: 5000000000 | H49: 43 | I49: 49 | J49: 3 | K49: 2023
A50: 49 | B50: ASSURANCES COMAR Côte d’Ivoire (COMAR-CI) | C50: COTE D'IVOIRE | D50: Non-vie | E50: Théophile MBORO ASSOGHO | F50: 42681 | G50: 8747780000 | H50: 20 | I50: 23 | J50: 4 | K50: 2023
A51: 50 | B51: ATLANTIQUE ASSURANCES COTE D'IVOIRE (AACI) | C51: COTE D'IVOIRE | D51: Non-vie | E51: Estelle TRAORE | F51: 1956 | G51: 3000000000 | H51: 45 | I51: 29 | J51: 7 | K51: 2023
A52: 51 | B52: AXA ASSURANCES | C52: COTE D'IVOIRE | D52: Non-vie | E52: Téyi LAWSON | F52: 29587 | G52: 5000006000 | H52: 34 | I52: 30 | J52: 0 | K52: 2023
A53: 52 | B53: LA LOYALE ASSURANCES | C53: COTE D'IVOIRE | D53: Non-vie | E53: BROU Yvette Mamy Koko | F53: 37926 | G53: 3486932497 | H53: 16 | I53: 20 | J53: 11 | K53: 2023
A54: 53 | B54: NOUVELLE SOCIETE INTERAFRICAINE D'ASSURANCES | C54: COTE D'IVOIRE | D54: Non-vie | E54: Magloire DOCHAMOU | F54: 34851 | G54: 7600000000 | H54: 78 | I54: 39 | J54: 3 | K54: 2023
A55: 54 | B55: SANLAM ASSURANCE CÔTE D'IVOIRE | C55: COTE D'IVOIRE | D55: Non-vie | E55: OUEDRAOGO Roland Zwewendpaogre | F55: 29252 | G55: 5000000000 | H55: 68 | I55: 54 | J55: 29 | K55: 2023
A56: 55 | B56: SERENITY ASSURANCES SA | C56: COTE D'IVOIRE | D56: Non-vie | E56: Maurice KIPPRE DIGBEU | F56: 39554 | G56: 3000000000 | H56: 24 | I56: 60 | J56: 23 | K56: 2023
A57: 56 | B57: SONAM GENERALE ASSURANCES COTE D'IVOIRE | C57: COTE D'IVOIRE | D57: Non-vie | E57: Papa Ibra DIENA | F57: 1987 | G57: 500000000 | H57: 14 | I57: 37 | J57: 14 | K57: 2023
A58: 57 | B58: SUNU ASSURANCES IARD | C58: COTE D'IVOIRE | D58: Non-vie | E58: Mamadou Moussa DIOUF | F58: 35529 | G58: 5000000000 | H58: 39 | I58: 27 | J58: 0 | K58: 2023
A59: 58 | B59: ASSURANCES INDUSTRIELLES ET COMMERCIALES SA | C59: GABON | D59: Non-vie | E59: Stephen MOUSSIROU | F59: 35431 | G59: 6000000000 | H59: 33 | I59: 28 | J59: 11 | K59: 2023
A60: 59 | B60: AXA ASSURANCES | C60: GABON | D60: Non-vie | E60: Marielle BAYE | F60: 27760 | G60: 5022465000 | H60: 24 | I60: 32 | J60: 18 | K60: 2023
A61: 60 | B61: CIF ASSURANCES-VIE MALI | C61: MALI | D61: Vie | E61: Corneille SANON | F61: 43096 | G61: 1167340000 | H61: 7 | I61: 1 | J61: 1 | K61: 2023
A62: 61 | B62: NSIA VIE MALI | C62: MALI | D62: Vie | E62: Lamine COULIBALY | F62: 39961 | G62: 7745170000 | H62: 3 | I62: 18 | J62: 2 | K62: 2023
A63: 62 | B63: SANLAM ASSURANCE VIE MALI | C63: MALI | D63: Vie | E63: Bikiry MAKANGUILE | F63: 40716 | G63: 3000000000 | H63: 7 | I63: 9 | J63: 14 | K63: 2023
A64: 63 | B64: SOCIETE NOUVELLE D'ASSURANCE VIE (SONAVIE) | C64: MALI | D64: Vie | E64: Adama DIALLO | F64: 35247 | G64: 5158990000 | H64: 15 | I64: 0 | J64: 22 | K64: 2023
A65: 64 | B65: AFG ASSURANCES MALI IARD | C65: MALI | D65: Non-vie | E65: CISSE Adam BA | F65: 41997 | G65: 3000000000 | H65: 8 | I65: 23 | J65: 14 | K65: 2023
A66: 65 | B66: ASSURANCES LAFIA SA | C66: MALI | D66: Non-vie | E66: Kadiatou KONE | F66: 30523 | G66: 3000000000 | H66: 14 | I66: 5 | J66: 14 | K66: 2023
A67: 66 | B67: COMPAGNIE D'ASSURANCE ET REASSURANCE SABU NYUMAN | C67: MALI | D67: Non-vie | E67: Abdrahamane KOUYATE | F67: 30772 | G67: 4379560000 | H67: 5 | I67: 21 | J67: 18 | K67: 2023
A68: 67 | B68: LES ASSURANCES BLEUES CNAR | C68: MALI | D68: Non-vie | E68: SANOGO Karim | F68: 25239 | G68: 3383897675 | H68: 13 | I68: 11 | J68: 14 | K68: 2023
A69: 68 | B69: NOUVELLE ALLIANCE D'ASSURANCES SA | C69: MALI | D69: Non-vie | E69: Abdoulaye TOURE | F69: 39133 | G69: 3000000000 | H69: 2 | I69: 8 | J69: 9 | K69: 2023
... A86: 85 | B86: SAAR VIE SENEGAL | C86: SENEGAL | D86: Vie | E86: BOPDA FONKO Cyrille | F86: 34074 | G86: 5000000000 | H86: 6 | I86: 4 | J86: 0 | K86: 2023
A87: 86 | B87: SONAM ASSURANCES VIE | C87: SENEGAL | D87: Vie | E87: Souleymane NIANE | F87: 25/09/20212 | G87: 3000000000 | H87: 12 | I87: 17 | J87: 18 | K87: 2023
A88: 87 | B88: SUNU ASSURANCES VIE SENEGAL | C88: SENEGAL | D88: Vie | E88: SY Adjaratou Khady NDAO | F88: 31658 | G88: 3000000000 | H88: 6 | I88: 30 | J88: 0 | K88: 2023
A89: 88 | B89: WAFA ASSURANCE VIE | C89: SENEGAL | D89: Vie | E89: Chakib HASSAN | F89: 41894 | G89: 3000000000 | H89: 11 | I89: 19 | J89: 0 | K89: 2023
A90: 89 | B90: ALLIANZ SENEGAL ASSURANCES | C90: SENEGAL | D90: Non-vie | E90: Alphonsine DASILVA | F90: 32121 | G90: 3000000000 | H90: 29 | I90: 28 | J90: 4 | K90: 2023
A91: 90 | B91: AMSA ASSURANCES | C91: SENEGAL | D91: Non-vie | E91: Fatou Quinet DIENG | F91: 28440 | G91: 5000000000 | H91: 30 | I91: 39 | J91: 0 | K91: 2023
A92: 91 | B92: ASKIA ASSURANCES SA | C92: SENEGAL | D92: Non-vie | E92: Oumou Niang TOURE | F92: 39413 | G92: 5000000000 | H92: 10 | I92: 9 | J92: 2 | K92: 2023
A93: 92 | B93: ASSURANCES LA PROVIDENCE DU SENEGAL SA | C93: SENEGAL | D93: Non-vie | E93: Ndèye Khady DIOP | F93: 42705 | G93: 5000000000 | H93: 10 | I93: 21 | J93: 5 | K93: 2023
A94: 93 | B94: AXA ASSURANCES SA | C94: SENEGAL | D94: Non-vie | E94: El Hadji Amar KEBE | F94: 26299 | G94: 5290000000 | H94: 27 | I94: 35 | J94: 2 | K94: 2023
A95: 94 | B95: FINAFRICA ASSURANCES SENEGAL | C95: SENEGAL | D95: Non-vie | E95: Ibrahima WANE | F95: 31841 | G95: 3000000000 | H95: 19 | I95: 27 | J95: 4 | K95: 2023
A96: 95 | B96: LA PREVOYANCE ASSURANCES SA | C96: SENEGAL | D96: Non-vie | E96: Mamour THIAW | F96: 31787 | G96: 4400000000 | H96: 23 | I96: 34 | J96: 34 | K96: 2023
A97: 96 | B97: MUTUELLE D'ASSURANCES AGRICOLES DU SENEGAL | C97: SENEGAL | D97: Non-vie | E97: Diouldé NIANE | F97: 23377 | G97: 4186827840 | K97: 2023
A98: 97 | B98: NSIA SENEGAL ASSURANCES | C98: SENEGAL | D98: Non-vie | E98: Momar SECK | F98: 37393 | G98: 3300000000 | H98: 12 | I98: 17 | J98: 10 | K98: 2023
A99: 98 | B99: SAAR Sénégal SA | C99: SENEGAL | D99: Non-vie | E99: BOPDA FONKOUA Cyrille | F99: 41985 | G99: 3000000000 | H99: 16 | I99: 4 | J99: 0 | K99: 2023
A100: 99 | B100: SONAC SA | C100: SENEGAL | D100: Non-vie | E100: Gora MANGANE | F100: 35650 | G100: 3000000000 | H100: 6 | I100: 12 | J100: 1 | K100: 2023
A101: 100 | B101: SONAM GENERALE ASSURANCES SA | C101: SENEGAL | D101: Non-vie | E101: Mamadou DIOP | F101: 37622 | G101: 3000000000 | H101: 10 | I101: 19 | J101: 11 | K101: 2023
A102: 101 | B102: SONAM ASSURANCES MUTUELLES | C102: SENEGAL | D102: Non-vie | E102: Diouldé NIANE | F102: 37622 | G102: 2000000000 | H102: 6 | I102: 20 | J102: 4 | K102: 2023
A103: 102 | B103: SUNU ASSURANCES IARD SENEGAL | C103: SENEGAL | D103: Non-vie | E103: Papa Amadou Néné MBAYE | F103: 38955 | G103: 3000000000 | H103: 12 | I103: 26 | J103: 2 | K103: 2023
A104: 103 | B104: WAFA ASSURANCE SA | C104: SENEGAL | D104: Non-vie | E104: Ibra KANE | G104: 4000000000 | K104: 2023
A105: 104 | B105: STAR VIE SA | C105: TCHAD | D105: Vie | E105: EL GONI BECHIR ADOUM | F105: 40941 | G105: 3064000000 | H105: 8 | I105: 17 | J105: 3 | K105: 2023
A106: 105 | B106: SOCIETE AFRICAINE D'ASSURANCES ET DE REASSURANCES | C106: TCHAD | D106: Non-vie | E106: FOSSO DIFFO EVARISTE | F106: 36900 | G106: 3090000000 | H106: 5 | I106: 21 | J106: 2 | K106: 2023
A107: 106 | B107: STAR NATIONALE SA | C107: TCHAD | D107: Non-vie | E107: ABDELKERIM BATIL TOGOI | F107: 28306 | G107: 3000000000 | H107: 11 | I107: 18 | J107: 55 | K107: 2023
A108: 107 | B108: CIF ASSURANCE -VIE TOGO | C108: TOGO | D108: Vie | E108: Fedy KOKOUMEH | F108: 39175 | G108: 5000000000 | H108: 7 | I108: 17 | J108: 2 | K108: 2023
A109: 108 | B109: GTA ASSURANCES VIE | C109: TOGO | D109: Vie | E109: Mabintou TRAORE | F109: 36892 | G109: 3000000000 | H109: 19 | I109: 2 | J109: 25 | K109: 2023
A110: 109 | B110: LA CITOYENNE VIE | C110: TOGO | D110: Vie | E110: Franck KLUTSE | F110: 43503 | G110: 937500000 | H110: 5 | I110: 6 | J110: 11 | K110: 2023
A111: 110 | B111: NSIA VIE TOGO | C111: TOGO | D111: Vie | E111: Yao Constant DJEKET | F111: 39045 | G111: 3000000000 | H111: 7 | I111: 19 | J111: 4 | K111: 2023
A112: 111 | B112: PRUDENTIAL BENEFICIAL LIFE INSURANCE S.A. | C112: TOGO | D112: Vie | E112: GBADAGO Justin QUAM | F112: 36770 | G112: 3000000000 | H112: 11 | I112: 25 | J112: 7 | K112: 2023
A113: 112 | B113: SUNU ASSURANCES VIE TOGO | C113: TOGO | D113: Vie | E113: Razack FASSASSI | F113: 36188 | G113: 3000000000 | H113: 17 | I113: 8 | J113: 7 | K113: 2023
A114: 113 | B114: FIDELIA ASSURANCES | C114: TOGO | D114: Non-vie | E114: Ayoko KUEVIAKOE | F114: 38202 | G114: 3037500000 | H114: 8 | I114: 11 | J114: 11 | K114: 2023
A115: 114 | B115: GTA ASSURANCES | C115: TOGO | D115: Non-vie | F115: 26665 | G115: 3000000000 | H115: 15 | I115: 35 | J115: 8 | K115: 2023
A116: 115 | B116: NOUVELLE SOCIETE INTERAFRICAINE D'ASSURANCES | C116: TOGO | D116: Non-vie | E116: Yao Constant DJEKET | F116: 38455 | G116: 3000000000 | H116: 12 | I116: 33 | J116: 8 | K116: 2023
A117: 116 | B117: SANLAM ASSURANCE | C117: TOGO | D117: Non-vie | E117: Simon Pierre GOUEM | F117: 39083 | G117: 3000000000 | H117: 24 | I117: 34 | J117: 6 | K117: 2023
A118: 117 | B118: SUNU ASSURANCES IARD - TOGO | C118: TOGO | D118: Non-vie | E118: Akpé Aku ACOLATSE | F118: 35431 | G118: 3120000000 | H118: 41 | I118: 13 | J118: 5 | K118: 2023

Sheet Emission&Prestations
A1: No enregistrement | B1: Societe | C1: Pays | D1: Branche | E1: Bloc | F1: Categorie | G1: Rubrique | H1: Mesure | I1: Annee | J1: Valeur (F CFA)
A2: 1 | B2: ATLANTIQUE ASSURANCE BENIN VIE | C2: BENIN | D2: Vie | E2: Emissions | F2: Individuelles | G2: Contrats en cas de vie | H2: Emissions nettes | I2: 2022 | J2: =IF('Emission&Prestations (brut)'!J2="","",'Emission&Prestations (brut)'!J2*1000)
A3: 1 | B3: ATLANTIQUE ASSURANCE BENIN VIE | C3: BENIN | D3: Vie | E3: Emissions | F3: Individuelles | G3: Contrats en cas de vie | H3: Emissions nettes | I3: 2023 | J3: =IF('Emission&Prestations (brut)'!J3="","",'Emission&Prestations (brut)'!J3*1000)
A4: 1 | B4: ATLANTIQUE ASSURANCE BENIN VIE | C4: BENIN | D4: Vie | E4: Emissions | F4: Individuelles | G4: Contrat en cas de décès | H4: Emissions nettes | I4: 2022 | J4: =IF('Emission&Prestations (brut)'!J4="","",'Emission&Prestations (brut)'!J4*1000)
A5: 1 | B5: ATLANTIQUE ASSURANCE BENIN VIE | C5: BENIN | D5: Vie | E5: Emissions | F5: Individuelles | G5: Contrat en cas de décès | H5: Emissions nettes | I5: 2023 | J5: =IF('Emission&Prestations (brut)'!J5="","",'Emission&Prestations (brut)'!J5*1000)
A6: 1 | B6: ATLANTIQUE ASSURANCE BENIN VIE | C6: BENIN | D6: Vie | E6: Emissions | F6: Individuelles | G6: Mixte | H6: Emissions nettes | I6: 2022 | J6: =IF('Emission&Prestations (brut)'!J6="","",'Emission&Prestations (brut)'!J6*1000)
A7: 1 | B7: ATLANTIQUE ASSURANCE BENIN VIE | C7: BENIN | D7: Vie | E7: Emissions | F7: Individuelles | G7: Mixte | H7: Emissions nettes | I7: 2023 | J7: =IF('Emission&Prestations (brut)'!J7="","",'Emission&Prestations (brut)'!J7*1000)
A8: 1 | B8: ATLANTIQUE ASSURANCE BENIN VIE | C8: BENIN | D8: Vie | E8: Emissions | F8: Individuelles | G8: Epargne | H8: Emissions nettes | I8: 2022 | J8: =IF('Emission&Prestations (brut)'!J8="","",'Emission&Prestations (brut)'!J8*1000)
A9: 1 | B9: ATLANTIQUE ASSURANCE BENIN VIE | C9: BENIN | D9: Vie | E9: Emissions | F9: Individuelles | G9: Epargne | H9: Emissions nettes | I9: 2023 | J9: =IF('Emission&Prestations (brut)'!J9="","",'Emission&Prestations (brut)'!J9*1000)
A10: 1 | B10: ATLANTIQUE ASSURANCE BENIN VIE | C10: BENIN | D10: Vie | E10: Emissions | F10: Individuelles | G10: Titre de capitalisation | H10: Emissions nettes | I10: 2022 | J10: =IF('Emission&Prestations (brut)'!J10="","",'Emission&Prestations (brut)'!J10*1000)
A11: 1 | B11: ATLANTIQUE ASSURANCE BENIN VIE | C11: BENIN | D11: Vie | E11: Emissions | F11: Individuelles | G11: Titre de capitalisation | H11: Emissions nettes | I11: 2023 | J11: =IF('Emission&Prestations (brut)'!J11="","",'Emission&Prestations (brut)'!J11*1000)
A12: 1 | B12: ATLANTIQUE ASSURANCE BENIN VIE | C12: BENIN | D12: Vie | E12: Emissions | F12: Individuelles | G12: Complémentaires | H12: Emissions nettes | I12: 2022 | J12: =IF('Emission&Prestations (brut)'!J12="","",'Emission&Prestations (brut)'!J12*1000)
A13: 1 | B13: ATLANTIQUE ASSURANCE BENIN VIE | C13: BENIN | D13: Vie | E13: Emissions | F13: Individuelles | G13: Complémentaires | H13: Emissions nettes | I13: 2023 | J13: =IF('Emission&Prestations (brut)'!J13="","",'Emission&Prestations (brut)'!J13*1000)
... A6687: 117 | B6687: SUNU ASSURANCES IARD - TOGO | C6687: TOGO | D6687: Non-vie | E6687: Sinistralite | F6687: Acceptations | G6687: Acceptations | H6687: Charges de sinistres (CS) | I6687: 2023 | J6687: =IF('Emission&Prestations (brut)'!J6687="","",'Emission&Prestations (brut)'!J6687*1000)

Sheet Chiffres clés
A1: No enregistrement | B1: Societe | C1: Pays | D1: Branche | E1: Rubrique | F1: Annee | G1: Valeur (F CFA)
A2: 1 | B2: ATLANTIQUE ASSURANCE BENIN VIE | C2: BENIN | D2: Vie | E2: Produits financiers nets | F2: 2022 | G2: =IF('Chiffres clés (brut)'!G2="","",'Chiffres clés (brut)'!G2*1000)
A3: 1 | B3: ATLANTIQUE ASSURANCE BENIN VIE | C3: BENIN | D3: Vie | E3: Produits financiers nets | F3: 2023 | G3: =IF('Chiffres clés (brut)'!G3="","",'Chiffres clés (brut)'!G3*1000)
A4: 1 | B4: ATLANTIQUE ASSURANCE BENIN VIE | C4: BENIN | D4: Vie | E4: Commissions | F4: 2022 | G4: =IF('Chiffres clés (brut)'!G4="","",'Chiffres clés (brut)'!G4*1000)
A5: 1 | B5: ATLANTIQUE ASSURANCE BENIN VIE | C5: BENIN | D5: Vie | E5: Commissions | F5: 2023 | G5: =IF('Chiffres clés (brut)'!G5="","",'Chiffres clés (brut)'!G5*1000)
A6: 1 | B6: ATLANTIQUE ASSURANCE BENIN VIE | C6: BENIN | D6: Vie | E6: Autres charges de l'exercice | F6: 2022 | G6: =IF('Chiffres clés (brut)'!G6="","",'Chiffres clés (brut)'!G6*1000)
A7: 1 | B7: ATLANTIQUE ASSURANCE BENIN VIE | C7: BENIN | D7: Vie | E7: Autres charges de l'exercice | F7: 2023 | G7: =IF('Chiffres clés (brut)'!G7="","",'Chiffres clés (brut)'!G7*1000)
A8: 1 | B8: ATLANTIQUE ASSURANCE BENIN VIE | C8: BENIN | D8: Vie | E8: Provisions mathématiques (clôture) | F8: 2022 | G8: =IF('Chiffres clés (brut)'!G8="","",'Chiffres clés (brut)'!G8*1000)
A9: 1 | B9: ATLANTIQUE ASSURANCE BENIN VIE | C9: BENIN | D9: Vie | E9: Provisions mathématiques (clôture) | F9: 2023 | G9: =IF('Chiffres clés (brut)'!G9="","",'Chiffres clés (brut)'!G9*1000)
A10: 1 | B10: ATLANTIQUE ASSURANCE BENIN VIE | C10: BENIN | D10: Vie | E10: Provisions mathématiques (ouverture) | F10: 2022 | G10: =IF('Chiffres clés (brut)'!G10="","",'Chiffres clés (brut)'!G10*1000)
A11: 1 | B11: ATLANTIQUE ASSURANCE BENIN VIE | C11: BENIN | D11: Vie | E11: Provisions mathématiques (ouverture) | F11: 2023 | G11: =IF('Chiffres clés (brut)'!G11="","",'Chiffres clés (brut)'!G11*1000)
A12: 1 | B12: ATLANTIQUE ASSURANCE BENIN VIE | C12: BENIN | D12: Vie | E12: Primes cédées aux réassureurs | F12: 2022 | G12: =IF('Chiffres clés (brut)'!G12="","",'Chiffres clés (brut)'!G12*1000)
A13: 1 | B13: ATLANTIQUE ASSURANCE BENIN VIE | C13: BENIN | D13: Vie | E13: Primes cédées aux réassureurs | F13: 2023 | G13: =IF('Chiffres clés (brut)'!G13="","",'Chiffres clés (brut)'!G13*1000)
... A3569: 117 | B3569: SUNU ASSURANCES IARD - TOGO | C3569: TOGO | D3569: Non-vie | E3569: Dont liquidités | F3569: 2023 | G3569: =IF('Chiffres clés (brut)'!G3569="","",'Chiffres clés (brut)'!G3569*1000)

Sheet Identification (brut)
A1: No enregistrement | B1: Societe | C1: Pays | D1: Branche | E1: Directeur general | F1: Date de creation | G1: Capital social (F CFA) | H1: Cadres | I1: Maitrise | J1: Employes | K1: Annee N | L1: Date d'import
A2: 1 | B2: ATLANTIQUE ASSURANCE BENIN VIE | C2: BENIN | D2: Vie | E2: Corinne GBENOU FOURN | F2: 34662 | G2: 3299350000 | H2: 9 | I2: 6 | J2: 2 | K2: 2023 | L2: 46290.674
A3: 2 | B3: CIF ASSURANCES VIE | C3: BENIN | D3: Vie | E3: Félix Edouard LADEKAN | F3: 41261 | G3: 1249280000 | H3: 11 | I3: 2 | J3: 2 | K3: 2023 | L3: 46290.674
A4: 3 | B4: L'AFRICAINE VIE BENIN | C4: BENIN | D4: Vie | E4: Hervé TCHIAKPE | F4: 38821 | G4: 3000000000 | H4: 10 | I4: 17 | J4: 2 | K4: 2023 | L4: 46290.674
A5: 4 | B5: NOUVELLE SOCIETE INTERAFRICAINE D'ASSURANCES VIE | C5: BENIN | D5: Vie | E5: DOSSOU FREJUS LIDWIN | F5: 38457 | G5: 3000000000 | H5: 14 | I5: 9 | J5: 2 | K5: 2023 | L5: 46290.674
A6: 5 | B6: SANLAM ASSURANCE VIE | C6: BENIN | D6: Vie | E6: Mariam NASSIROU | F6: 35230 | G6: 3000000000 | H6: 16 | I6: 49 | J6: 0 | K6: 2023 | L6: 46290.674
A7: 6 | B7: SUNU ASSURANCES VIE BENIN | C7: BENIN | D7: Vie | E7: Souleymane Wassila FAYE | F7: 34655 | G7: 3000000000 | H7: 37 | I7: 6 | J7: 1 | K7: 2023 | L7: 46290.674
A8: 7 | B8: ATLANTIQUE ASSURANCES BENIN IARDT | C8: BENIN | D8: Non-vie | E8: AYIVI-ELEGBEDE Florence | F8: 42459 | G8: 5000000000 | H8: 21 | I8: 23 | J8: 4 | K8: 2023 | L8: 46290.674
A9: 8 | B9: L'AFRICAINE DES ASSURANCES | C9: BENIN | D9: Non-vie | E9: Kenneth ELEGBEDE | F9: 35739 | G9: 4493470000 | H9: 29 | I9: 48 | J9: 7 | K9: 2023 | L9: 46290.674
A10: 9 | B10: LA GENERALE DES ASSURANCES | C10: BENIN | D10: Non-vie | E10: Gaston Arnaud de SOUZA | F10: 36280 | G10: 3000000000 | H10: 7 | I10: 9 | J10: 9 | K10: 2023 | L10: 46290.674
A11: 10 | B11: NOBILA ASSURANCES SA | C11: BENIN | D11: Non-vie | E11: André A. AZIBLI | F11: 38630 | G11: 3000000000 | H11: 9 | I11: 8 | J11: 11 | K11: 2023 | L11: 46290.674
A12: 11 | B12: NOUVELLE SOCIETE INTERAFRICAINE D'ASSURANCES | C12: BENIN | D12: Non-vie | E12: AGBOTA Fabrice | F12: 35796 | G12: 4800000000 | H12: 27 | I12: 25 | J12: 4 | K12: 2023 | L12: 46290.674
A13: 12 | B13: SANLAM ASSURANCE | C13: BENIN | D13: Non-vie | E13: Edmond DOSSOU | F13: 40420 | G13: 3000000000 | H13: 12 | I13: 22 | J13: 2 | K13: 2023 | L13: 46290.674
... A48: 47 | B48: ALLIANZ CÔTE D'IVOIRE ASSURANCES | C48: COTE D'IVOIRE | D48: Non-vie | E48: Mamadou G. K. KONE | F48: 27760 | G48: 3000000000 | H48: 55 | I48: 49 | J48: 2 | K48: 2023 | L48: 46290.674
A49: 48 | B49: AMSA ASSURANCES | C49: COTE D'IVOIRE | D49: Non-vie | E49: Yatassaye SAMBA | F49: En 1972 | G49: 5000000000 | H49: 43 | I49: 49 | J49: 3 | K49: 2023 | L49: 46290.674
A50: 49 | B50: ASSURANCES COMAR Côte d’Ivoire (COMAR-CI) | C50: COTE D'IVOIRE | D50: Non-vie | E50: Théophile MBORO ASSOGHO | F50: 42681 | G50: 8747780000 | H50: 20 | I50: 23 | J50: 4 | K50: 2023 | L50: 46290.674
A51: 50 | B51: ATLANTIQUE ASSURANCES COTE D'IVOIRE (AACI) | C51: COTE D'IVOIRE | D51: Non-vie | E51: Estelle TRAORE | F51: 1956 | G51: 3000000000 | H51: 45 | I51: 29 | J51: 7 | K51: 2023 | L51: 46290.674
A52: 51 | B52: AXA ASSURANCES | C52: COTE D'IVOIRE | D52: Non-vie | E52: Téyi LAWSON | F52: 29587 | G52: 5000006000 | H52: 34 | I52: 30 | J52: 0 | K52: 2023 | L52: 46290.674
A53: 52 | B53: LA LOYALE ASSURANCES | C53: COTE D'IVOIRE | D53: Non-vie | E53: BROU Yvette Mamy Koko | F53: 37926 | G53: 3486932497 | H53: 16 | I53: 20 | J53: 11 | K53: 2023 | L53: 46290.674
A54: 53 | B54: NOUVELLE SOCIETE INTERAFRICAINE D'ASSURANCES | C54: COTE D'IVOIRE | D54: Non-vie | E54: Magloire DOCHAMOU | F54: 34851 | G54: 7600000000 | H54: 78 | I54: 39 | J54: 3 | K54: 2023 | L54: 46290.674
A55: 54 | B55: SANLAM ASSURANCE CÔTE D'IVOIRE | C55: COTE D'IVOIRE | D55: Non-vie | E55: OUEDRAOGO Roland Zwewendpaogre | F55: 29252 | G55: 5000000000 | H55: 68 | I55: 54 | J55: 29 | K55: 2023 | L55: 46290.674
A56: 55 | B56: SERENITY ASSURANCES SA | C56: COTE D'IVOIRE | D56: Non-vie | E56: Maurice KIPPRE DIGBEU | F56: 39554 | G56: 3000000000 | H56: 24 | I56: 60 | J56: 23 | K56: 2023 | L56: 46290.674
A57: 56 | B57: SONAM GENERALE ASSURANCES COTE D'IVOIRE | C57: COTE D'IVOIRE | D57: Non-vie | E57: Papa Ibra DIENA | F57: 1987 | G57: 500000000 | H57: 14 | I57: 37 | J57: 14 | K57: 2023 | L57: 46290.674
A58: 57 | B58: SUNU ASSURANCES IARD | C58: COTE D'IVOIRE | D58: Non-vie | E58: Mamadou Moussa DIOUF | F58: 35529 | G58: 5000000000 | H58: 39 | I58: 27 | J58: 0 | K58: 2023 | L58: 46290.674
A59: 58 | B59: ASSURANCES INDUSTRIELLES ET COMMERCIALES SA | C59: GABON | D59: Non-vie | E59: Stephen MOUSSIROU | F59: 35431 | G59: 6000000000 | H59: 33 | I59: 28 | J59: 11 | K59: 2023 | L59: 46290.674
A60: 59 | B60: AXA ASSURANCES | C60: GABON | D60: Non-vie | E60: Marielle BAYE | F60: 27760 | G60: 5022465000 | H60: 24 | I60: 32 | J60: 18 | K60: 2023 | L60: 46290.674
A61: 60 | B61: CIF ASSURANCES-VIE MALI | C61: MALI | D61: Vie | E61: Corneille SANON | F61: 43096 | G61: 1167340000 | H61: 7 | I61: 1 | J61: 1 | K61: 2023 | L61: 46290.674
A62: 61 | B62: NSIA VIE MALI | C62: MALI | D62: Vie | E62: Lamine COULIBALY | F62: 39961 | G62: 7745170000 | H62: 3 | I62: 18 | J62: 2 | K62: 2023 | L62: 46290.674
A63: 62 | B63: SANLAM ASSURANCE VIE MALI | C63: MALI | D63: Vie | E63: Bikiry MAKANGUILE | F63: 40716 | G63: 3000000000 | H63: 7 | I63: 9 | J63: 14 | K63: 2023 | L63: 46290.674
A64: 63 | B64: SOCIETE NOUVELLE D'ASSURANCE VIE (SONAVIE) | C64: MALI | D64: Vie | E64: Adama DIALLO | F64: 35247 | G64: 5158990000 | H64: 15 | I64: 0 | J64: 22 | K64: 2023 | L64: 46290.674
A65: 64 | B65: AFG ASSURANCES MALI IARD | C65: MALI | D65: Non-vie | E65: CISSE Adam BA | F65: 41997 | G65: 3000000000 | H65: 8 | I65: 23 | J65: 14 | K65: 2023 | L65: 46290.674
A66: 65 | B66: ASSURANCES LAFIA SA | C66: MALI | D66: Non-vie | E66: Kadiatou KONE | F66: 30523 | G66: 3000000000 | H66: 14 | I66: 5 | J66: 14 | K66: 2023 | L66: 46290.674
A67: 66 | B67: COMPAGNIE D'ASSURANCE ET REASSURANCE SABU NYUMAN | C67: MALI | D67: Non-vie | E67: Abdrahamane KOUYATE | F67: 30772 | G67: 4379560000 | H67: 5 | I67: 21 | J67: 18 | K67: 2023 | L67: 46290.674
A68: 67 | B68: LES ASSURANCES BLEUES CNAR | C68: MALI | D68: Non-vie | E68: SANOGO Karim | F68: 25239 | G68: 3383897675 | H68: 13 | I68: 11 | J68: 14 | K68: 2023 | L68: 46290.674
A69: 68 | B69: NOUVELLE ALLIANCE D'ASSURANCES SA | C69: MALI | D69: Non-vie | E69: Abdoulaye TOURE | F69: 39133 | G69: 3000000000 | H69: 2 | I69: 8 | J69: 9 | K69: 2023 | L69: 46290.674
... A86: 85 | B86: SAAR VIE SENEGAL | C86: SENEGAL | D86: Vie | E86: BOPDA FONKO Cyrille | F86: 34074 | G86: 5000000000 | H86: 6 | I86: 4 | J86: 0 | K86: 2023 | L86: 46290.674
A87: 86 | B87: SONAM ASSURANCES VIE | C87: SENEGAL | D87: Vie | E87: Souleymane NIANE | F87: 25/09/20212 | G87: 3000000000 | H87: 12 | I87: 17 | J87: 18 | K87: 2023 | L87: 46290.674
A88: 87 | B88: SUNU ASSURANCES VIE SENEGAL | C88: SENEGAL | D88: Vie | E88: SY Adjaratou Khady NDAO | F88: 31658 | G88: 3000000000 | H88: 6 | I88: 30 | J88: 0 | K88: 2023 | L88: 46290.674
A89: 88 | B89: WAFA ASSURANCE VIE | C89: SENEGAL | D89: Vie | E89: Chakib HASSAN | F89: 41894 | G89: 3000000000 | H89: 11 | I89: 19 | J89: 0 | K89: 2023 | L89: 46290.674
A90: 89 | B90: ALLIANZ SENEGAL ASSURANCES | C90: SENEGAL | D90: Non-vie | E90: Alphonsine DASILVA | F90: 32121 | G90: 3000000000 | H90: 29 | I90: 28 | J90: 4 | K90: 2023 | L90: 46290.674
A91: 90 | B91: AMSA ASSURANCES | C91: SENEGAL | D91: Non-vie | E91: Fatou Quinet DIENG | F91: 28440 | G91: 5000000000 | H91: 30 | I91: 39 | J91: 0 | K91: 2023 | L91: 46290.674
A92: 91 | B92: ASKIA ASSURANCES SA | C92: SENEGAL | D92: Non-vie | E92: Oumou Niang TOURE | F92: 39413 | G92: 5000000000 | H92: 10 | I92: 9 | J92: 2 | K92: 2023 | L92: 46290.674
A93: 92 | B93: ASSURANCES LA PROVIDENCE DU SENEGAL SA | C93: SENEGAL | D93: Non-vie | E93: Ndèye Khady DIOP | F93: 42705 | G93: 5000000000 | H93: 10 | I93: 21 | J93: 5 | K93: 2023 | L93: 46290.674
A94: 93 | B94: AXA ASSURANCES SA | C94: SENEGAL | D94: Non-vie | E94: El Hadji Amar KEBE | F94: 26299 | G94: 5290000000 | H94: 27 | I94: 35 | J94: 2 | K94: 2023 | L94: 46290.674
A95: 94 | B95: FINAFRICA ASSURANCES SENEGAL | C95: SENEGAL | D95: Non-vie | E95: Ibrahima WANE | F95: 31841 | G95: 3000000000 | H95: 19 | I95: 27 | J95: 4 | K95: 2023 | L95: 46290.674
A96: 95 | B96: LA PREVOYANCE ASSURANCES SA | C96: SENEGAL | D96: Non-vie | E96: Mamour THIAW | F96: 31787 | G96: 4400000000 | H96: 23 | I96: 34 | J96: 34 | K96: 2023 | L96: 46290.674
A97: 96 | B97: MUTUELLE D'ASSURANCES AGRICOLES DU SENEGAL | C97: SENEGAL | D97: Non-vie | E97: Diouldé NIANE | F97: 23377 | G97: 4186827840 | K97: 2023 | L97: 46290.674
A98: 97 | B98: NSIA SENEGAL ASSURANCES | C98: SENEGAL | D98: Non-vie | E98: Momar SECK | F98: 37393 | G98: 3300000000 | H98: 12 | I98: 17 | J98: 10 | K98: 2023 | L98: 46290.674
A99: 98 | B99: SAAR Sénégal SA | C99: SENEGAL | D99: Non-vie | E99: BOPDA FONKOUA Cyrille | F99: 41985 | G99: 3000000000 | H99: 16 | I99: 4 | J99: 0 | K99: 2023 | L99: 46290.674
A100: 99 | B100: SONAC SA | C100: SENEGAL | D100: Non-vie | E100: Gora MANGANE | F100: 35650 | G100: 3000000000 | H100: 6 | I100: 12 | J100: 1 | K100: 2023 | L100: 46290.674
A101: 100 | B101: SONAM GENERALE ASSURANCES SA | C101: SENEGAL | D101: Non-vie | E101: Mamadou DIOP | F101: 37622 | G101: 3000000000 | H101: 10 | I101: 19 | J101: 11 | K101: 2023 | L101: 46290.674
A102: 101 | B102: SONAM ASSURANCES MUTUELLES | C102: SENEGAL | D102: Non-vie | E102: Diouldé NIANE | F102: 37622 | G102: 2000000000 | H102: 6 | I102: 20 | J102: 4 | K102: 2023 | L102: 46290.674
A103: 102 | B103: SUNU ASSURANCES IARD SENEGAL | C103: SENEGAL | D103: Non-vie | E103: Papa Amadou Néné MBAYE | F103: 38955 | G103: 3000000000 | H103: 12 | I103: 26 | J103: 2 | K103: 2023 | L103: 46290.674
A104: 103 | B104: WAFA ASSURANCE SA | C104: SENEGAL | D104: Non-vie | E104: Ibra KANE | G104: 4000000000 | K104: 2023 | L104: 46290.674
A105: 104 | B105: STAR VIE SA | C105: TCHAD | D105: Vie | E105: EL GONI BECHIR ADOUM | F105: 40941 | G105: 3064000000 | H105: 8 | I105: 17 | J105: 3 | K105: 2023 | L105: 46290.674
A106: 105 | B106: SOCIETE AFRICAINE D'ASSURANCES ET DE REASSURANCES | C106: TCHAD | D106: Non-vie | E106: FOSSO DIFFO EVARISTE | F106: 36900 | G106: 3090000000 | H106: 5 | I106: 21 | J106: 2 | K106: 2023 | L106: 46290.674
A107: 106 | B107: STAR NATIONALE SA | C107: TCHAD | D107: Non-vie | E107: ABDELKERIM BATIL TOGOI | F107: 28306 | G107: 3000000000 | H107: 11 | I107: 18 | J107: 55 | K107: 2023 | L107: 46290.674
A108: 107 | B108: CIF ASSURANCE -VIE TOGO | C108: TOGO | D108: Vie | E108: Fedy KOKOUMEH | F108: 39175 | G108: 5000000000 | H108: 7 | I108: 17 | J108: 2 | K108: 2023 | L108: 46290.674
A109: 108 | B109: GTA ASSURANCES VIE | C109: TOGO | D109: Vie | E109: Mabintou TRAORE | F109: 36892 | G109: 3000000000 | H109: 19 | I109: 2 | J109: 25 | K109: 2023 | L109: 46290.674
A110: 109 | B110: LA CITOYENNE VIE | C110: TOGO | D110: Vie | E110: Franck KLUTSE | F110: 43503 | G110: 937500000 | H110: 5 | I110: 6 | J110: 11 | K110: 2023 | L110: 46290.674
A111: 110 | B111: NSIA VIE TOGO | C111: TOGO | D111: Vie | E111: Yao Constant DJEKET | F111: 39045 | G111: 3000000000 | H111: 7 | I111: 19 | J111: 4 | K111: 2023 | L111: 46290.674
A112: 111 | B112: PRUDENTIAL BENEFICIAL LIFE INSURANCE S.A. | C112: TOGO | D112: Vie | E112: GBADAGO Justin QUAM | F112: 36770 | G112: 3000000000 | H112: 11 | I112: 25 | J112: 7 | K112: 2023 | L112: 46290.674
A113: 112 | B113: SUNU ASSURANCES VIE TOGO | C113: TOGO | D113: Vie | E113: Razack FASSASSI | F113: 36188 | G113: 3000000000 | H113: 17 | I113: 8 | J113: 7 | K113: 2023 | L113: 46290.674
A114: 113 | B114: FIDELIA ASSURANCES | C114: TOGO | D114: Non-vie | E114: Ayoko KUEVIAKOE | F114: 38202 | G114: 3037500000 | H114: 8 | I114: 11 | J114: 11 | K114: 2023 | L114: 46290.674
A115: 114 | B115: GTA ASSURANCES | C115: TOGO | D115: Non-vie | F115: 26665 | G115: 3000000000 | H115: 15 | I115: 35 | J115: 8 | K115: 2023 | L115: 46290.674
A116: 115 | B116: NOUVELLE SOCIETE INTERAFRICAINE D'ASSURANCES | C116: TOGO | D116: Non-vie | E116: Yao Constant DJEKET | F116: 38455 | G116: 3000000000 | H116: 12 | I116: 33 | J116: 8 | K116: 2023 | L116: 46290.674
A117: 116 | B117: SANLAM ASSURANCE | C117: TOGO | D117: Non-vie | E117: Simon Pierre GOUEM | F117: 39083 | G117: 3000000000 | H117: 24 | I117: 34 | J117: 6 | K117: 2023 | L117: 46290.674
A118: 117 | B118: SUNU ASSURANCES IARD - TOGO | C118: TOGO | D118: Non-vie | E118: Akpé Aku ACOLATSE | F118: 35431 | G118: 3120000000 | H118: 41 | I118: 13 | J118: 5 | K118: 2023 | L118: 46290.674

Sheet Emission&Prestations (brut)
A1: No enregistrement | B1: Societe | C1: Pays | D1: Branche | E1: Bloc | F1: Categorie | G1: Rubrique | H1: Mesure | I1: Annee | J1: Valeur (milliers F CFA) | K1: Cellule source
A2: 1 | B2: ATLANTIQUE ASSURANCE BENIN VIE | C2: BENIN | D2: Vie | E2: Emissions | F2: Individuelles | G2: Contrats en cas de vie | H2: Emissions nettes | I2: 2022 | J2: 0 | K2: PDF p. 15 (page imprimee 10)
A3: 1 | B3: ATLANTIQUE ASSURANCE BENIN VIE | C3: BENIN | D3: Vie | E3: Emissions | F3: Individuelles | G3: Contrats en cas de vie | H3: Emissions nettes | I3: 2023 | J3: 0 | K3: PDF p. 15 (page imprimee 10)
A4: 1 | B4: ATLANTIQUE ASSURANCE BENIN VIE | C4: BENIN | D4: Vie | E4: Emissions | F4: Individuelles | G4: Contrat en cas de décès | H4: Emissions nettes | I4: 2022 | J4: 565876 | K4: PDF p. 15 (page imprimee 10)
A5: 1 | B5: ATLANTIQUE ASSURANCE BENIN VIE | C5: BENIN | D5: Vie | E5: Emissions | F5: Individuelles | G5: Contrat en cas de décès | H5: Emissions nettes | I5: 2023 | J5: 1177646 | K5: PDF p. 15 (page imprimee 10)
A6: 1 | B6: ATLANTIQUE ASSURANCE BENIN VIE | C6: BENIN | D6: Vie | E6: Emissions | F6: Individuelles | G6: Mixte | H6: Emissions nettes | I6: 2022 | J6: 938229 | K6: PDF p. 15 (page imprimee 10)
A7: 1 | B7: ATLANTIQUE ASSURANCE BENIN VIE | C7: BENIN | D7: Vie | E7: Emissions | F7: Individuelles | G7: Mixte | H7: Emissions nettes | I7: 2023 | J7: 782690 | K7: PDF p. 15 (page imprimee 10)
A8: 1 | B8: ATLANTIQUE ASSURANCE BENIN VIE | C8: BENIN | D8: Vie | E8: Emissions | F8: Individuelles | G8: Epargne | H8: Emissions nettes | I8: 2022 | J8: 613008 | K8: PDF p. 15 (page imprimee 10)
A9: 1 | B9: ATLANTIQUE ASSURANCE BENIN VIE | C9: BENIN | D9: Vie | E9: Emissions | F9: Individuelles | G9: Epargne | H9: Emissions nettes | I9: 2023 | J9: 453206 | K9: PDF p. 15 (page imprimee 10)
A10: 1 | B10: ATLANTIQUE ASSURANCE BENIN VIE | C10: BENIN | D10: Vie | E10: Emissions | F10: Individuelles | G10: Titre de capitalisation | H10: Emissions nettes | I10: 2022 | J10: 0 | K10: PDF p. 15 (page imprimee 10)
A11: 1 | B11: ATLANTIQUE ASSURANCE BENIN VIE | C11: BENIN | D11: Vie | E11: Emissions | F11: Individuelles | G11: Titre de capitalisation | H11: Emissions nettes | I11: 2023 | J11: 0 | K11: PDF p. 15 (page imprimee 10)
A12: 1 | B12: ATLANTIQUE ASSURANCE BENIN VIE | C12: BENIN | D12: Vie | E12: Emissions | F12: Individuelles | G12: Complémentaires | H12: Emissions nettes | I12: 2022 | J12: 50737 | K12: PDF p. 15 (page imprimee 10)
A13: 1 | B13: ATLANTIQUE ASSURANCE BENIN VIE | C13: BENIN | D13: Vie | E13: Emissions | F13: Individuelles | G13: Complémentaires | H13: Emissions nettes | I13: 2023 | J13: 35565 | K13: PDF p. 15 (page imprimee 10)
... A78: 2 | B78: CIF ASSURANCES VIE | C78: BENIN | D78: Vie | E78: Emissions | F78: Acceptations | G78: Acceptations | H78: Emissions nettes | I78: 2022 | J78: 0 | K78: PDF p. 16 (page imprimee 11)
A79: 2 | B79: CIF ASSURANCES VIE | C79: BENIN | D79: Vie | E79: Emissions | F79: Acceptations | G79: Acceptations | H79: Emissions nettes | I79: 2023 | K79: PDF p. 16 (page imprimee 11)
A80: 2 | B80: CIF ASSURANCES VIE | C80: BENIN | D80: Vie | E80: Prestations | F80: Individuelles | G80: Contrats en cas de vie | H80: Prestations versees | I80: 2022 | J80: 0 | K80: PDF p. 16 (page imprimee 11)
A81: 2 | B81: CIF ASSURANCES VIE | C81: BENIN | D81: Vie | E81: Prestations | F81: Individuelles | G81: Contrats en cas de vie | H81: Prestations versees | I81: 2023 | J81: 0 | K81: PDF p. 16 (page imprimee 11)
A82: 2 | B82: CIF ASSURANCES VIE | C82: BENIN | D82: Vie | E82: Prestations | F82: Individuelles | G82: Contrat en cas de décès | H82: Prestations versees | I82: 2022 | J82: 290759 | K82: PDF p. 16 (page imprimee 11)
A83: 2 | B83: CIF ASSURANCES VIE | C83: BENIN | D83: Vie | E83: Prestations | F83: Individuelles | G83: Contrat en cas de décès | H83: Prestations versees | I83: 2023 | J83: 267423 | K83: PDF p. 16 (page imprimee 11)
A84: 2 | B84: CIF ASSURANCES VIE | C84: BENIN | D84: Vie | E84: Prestations | F84: Individuelles | G84: Mixte | H84: Prestations versees | I84: 2022 | J84: 0 | K84: PDF p. 16 (page imprimee 11)
A85: 2 | B85: CIF ASSURANCES VIE | C85: BENIN | D85: Vie | E85: Prestations | F85: Individuelles | G85: Mixte | H85: Prestations versees | I85: 2023 | J85: 0 | K85: PDF p. 16 (page imprimee 11)
A86: 2 | B86: CIF ASSURANCES VIE | C86: BENIN | D86: Vie | E86: Prestations | F86: Individuelles | G86: Epargne | H86: Prestations versees | I86: 2022 | J86: 139050 | K86: PDF p. 16 (page imprimee 11)
A87: 2 | B87: CIF ASSURANCES VIE | C87: BENIN | D87: Vie | E87: Prestations | F87: Individuelles | G87: Epargne | H87: Prestations versees | I87: 2023 | J87: 126867 | K87: PDF p. 16 (page imprimee 11)
A88: 2 | B88: CIF ASSURANCES VIE | C88: BENIN | D88: Vie | E88: Prestations | F88: Individuelles | G88: Titre de capitalisation | H88: Prestations versees | I88: 2022 | J88: 0 | K88: PDF p. 16 (page imprimee 11)
A89: 2 | B89: CIF ASSURANCES VIE | C89: BENIN | D89: Vie | E89: Prestations | F89: Individuelles | G89: Titre de capitalisation | H89: Prestations versees | I89: 2023 | J89: 0 | K89: PDF p. 16 (page imprimee 11)
A90: 2 | B90: CIF ASSURANCES VIE | C90: BENIN | D90: Vie | E90: Prestations | F90: Individuelles | G90: Complémentaires | H90: Prestations versees | I90: 2022 | J90: 0 | K90: PDF p. 16 (page imprimee 11)
A91: 2 | B91: CIF ASSURANCES VIE | C91: BENIN | D91: Vie | E91: Prestations | F91: Individuelles | G91: Complémentaires | H91: Prestations versees | I91: 2023 | J91: 0 | K91: PDF p. 16 (page imprimee 11)
... A1000: 18 | B1000: GENERALE DES ASSURANCES | C1000: BURKINA FASO | D1000: Non-vie | E1000: Sinistralite | F1000: Acceptations | G1000: Acceptations | H1000: Charges de sinistres (CS) | I1000: 2022 | J1000: 0 | K1000: PDF p. 37 (page imprimee 32)
A1001: 18 | B1001: GENERALE DES ASSURANCES | C1001: BURKINA FASO | D1001: Non-vie | E1001: Sinistralite | F1001: Acceptations | G1001: Acceptations | H1001: Charges de sinistres (CS) | I1001: 2023 | K1001: PDF p. 37 (page imprimee 32)
A1002: 19 | B1002: RAYNAL ASSURANCES IARD | C1002: BURKINA FASO | D1002: Non-vie | E1002: Emissions | F1002: Affaires directes | G1002: Accidents corporels et maladie | H1002: Primes émises | I1002: 2022 | J1002: 1289545 | K1002: PDF p. 38 (page imprimee 33)
A1003: 19 | B1003: RAYNAL ASSURANCES IARD | C1003: BURKINA FASO | D1003: Non-vie | E1003: Emissions | F1003: Affaires directes | G1003: Accidents corporels et maladie | H1003: Primes acquises (PA) | I1003: 2022 | J1003: 1530348 | K1003: PDF p. 38 (page imprimee 33)
A1004: 19 | B1004: RAYNAL ASSURANCES IARD | C1004: BURKINA FASO | D1004: Non-vie | E1004: Emissions | F1004: Affaires directes | G1004: Accidents corporels et maladie | H1004: Primes émises | I1004: 2023 | J1004: 1489879 | K1004: PDF p. 38 (page imprimee 33)
A1005: 19 | B1005: RAYNAL ASSURANCES IARD | C1005: BURKINA FASO | D1005: Non-vie | E1005: Emissions | F1005: Affaires directes | G1005: Accidents corporels et maladie | H1005: Primes acquises (PA) | I1005: 2023 | J1005: 1525722 | K1005: PDF p. 38 (page imprimee 33)
A1006: 19 | B1006: RAYNAL ASSURANCES IARD | C1006: BURKINA FASO | D1006: Non-vie | E1006: Emissions | F1006: Affaires directes | G1006: Automobile : Responsabilité Civile | H1006: Primes émises | I1006: 2022 | J1006: 1748038 | K1006: PDF p. 38 (page imprimee 33)
A1007: 19 | B1007: RAYNAL ASSURANCES IARD | C1007: BURKINA FASO | D1007: Non-vie | E1007: Emissions | F1007: Affaires directes | G1007: Automobile : Responsabilité Civile | H1007: Primes acquises (PA) | I1007: 2022 | J1007: 1735265 | K1007: PDF p. 38 (page imprimee 33)
A1008: 19 | B1008: RAYNAL ASSURANCES IARD | C1008: BURKINA FASO | D1008: Non-vie | E1008: Emissions | F1008: Affaires directes | G1008: Automobile : Responsabilité Civile | H1008: Primes émises | I1008: 2023 | J1008: 1760841 | K1008: PDF p. 38 (page imprimee 33)
A1009: 19 | B1009: RAYNAL ASSURANCES IARD | C1009: BURKINA FASO | D1009: Non-vie | E1009: Emissions | F1009: Affaires directes | G1009: Automobile : Responsabilité Civile | H1009: Primes acquises (PA) | I1009: 2023 | J1009: 1791382 | K1009: PDF p. 38 (page imprimee 33)
A1010: 19 | B1010: RAYNAL ASSURANCES IARD | C1010: BURKINA FASO | D1010: Non-vie | E1010: Emissions | F1010: Affaires directes | G1010: Automobile : Autres risques | H1010: Primes émises | I1010: 2022 | J1010: 1553129 | K1010: PDF p. 38 (page imprimee 33)
A1011: 19 | B1011: RAYNAL ASSURANCES IARD | C1011: BURKINA FASO | D1011: Non-vie | E1011: Emissions | F1011: Affaires directes | G1011: Automobile : Autres risques | H1011: Primes acquises (PA) | I1011: 2022 | J1011: 1589873 | K1011: PDF p. 38 (page imprimee 33)
A1012: 19 | B1012: RAYNAL ASSURANCES IARD | C1012: BURKINA FASO | D1012: Non-vie | E1012: Emissions | F1012: Affaires directes | G1012: Automobile : Autres risques | H1012: Primes émises | I1012: 2023 | J1012: 1670331 | K1012: PDF p. 38 (page imprimee 33)
A1013: 19 | B1013: RAYNAL ASSURANCES IARD | C1013: BURKINA FASO | D1013: Non-vie | E1013: Emissions | F1013: Affaires directes | G1013: Automobile : Autres risques | H1013: Primes acquises (PA) | I1013: 2023 | J1013: 1675724 | K1013: PDF p. 38 (page imprimee 33)
... A1441: 26 | B1441: SUNU ASSURANCES VIE CAMEROUN | C1441: CAMEROUN | D1441: Vie | E1441: Prestations | F1441: Acceptations | G1441: Acceptations | H1441: Prestations versees | I1441: 2023 | J1441: 0 | K1441: PDF p. 47 (page imprimee 42)
A1442: 27 | B1442: WAFA ASSURANCE VIE CAMEROUN | C1442: CAMEROUN | D1442: Vie | E1442: Emissions | F1442: Individuelles | G1442: Contrats en cas de vie | H1442: Emissions nettes | I1442: 2022 | K1442: PDF p. 48 (page imprimee 43)
A1443: 27 | B1443: WAFA ASSURANCE VIE CAMEROUN | C1443: CAMEROUN | D1443: Vie | E1443: Emissions | F1443: Individuelles | G1443: Contrats en cas de vie | H1443: Emissions nettes | I1443: 2023 | J1443: 0 | K1443: PDF p. 48 (page imprimee 43)
A1444: 27 | B1444: WAFA ASSURANCE VIE CAMEROUN | C1444: CAMEROUN | D1444: Vie | E1444: Emissions | F1444: Individuelles | G1444: Contrat en cas de décès | H1444: Emissions nettes | I1444: 2022 | K1444: PDF p. 48 (page imprimee 43)
A1445: 27 | B1445: WAFA ASSURANCE VIE CAMEROUN | C1445: CAMEROUN | D1445: Vie | E1445: Emissions | F1445: Individuelles | G1445: Contrat en cas de décès | H1445: Emissions nettes | I1445: 2023 | J1445: 1934152 | K1445: PDF p. 48 (page imprimee 43)
A1446: 27 | B1446: WAFA ASSURANCE VIE CAMEROUN | C1446: CAMEROUN | D1446: Vie | E1446: Emissions | F1446: Individuelles | G1446: Mixte | H1446: Emissions nettes | I1446: 2022 | K1446: PDF p. 48 (page imprimee 43)
A1447: 27 | B1447: WAFA ASSURANCE VIE CAMEROUN | C1447: CAMEROUN | D1447: Vie | E1447: Emissions | F1447: Individuelles | G1447: Mixte | H1447: Emissions nettes | I1447: 2023 | J1447: 10344 | K1447: PDF p. 48 (page imprimee 43)
A1448: 27 | B1448: WAFA ASSURANCE VIE CAMEROUN | C1448: CAMEROUN | D1448: Vie | E1448: Emissions | F1448: Individuelles | G1448: Epargne | H1448: Emissions nettes | I1448: 2022 | K1448: PDF p. 48 (page imprimee 43)
A1449: 27 | B1449: WAFA ASSURANCE VIE CAMEROUN | C1449: CAMEROUN | D1449: Vie | E1449: Emissions | F1449: Individuelles | G1449: Epargne | H1449: Emissions nettes | I1449: 2023 | J1449: 2681031 | K1449: PDF p. 48 (page imprimee 43)
A1450: 27 | B1450: WAFA ASSURANCE VIE CAMEROUN | C1450: CAMEROUN | D1450: Vie | E1450: Emissions | F1450: Individuelles | G1450: Titre de capitalisation | H1450: Emissions nettes | I1450: 2022 | K1450: PDF p. 48 (page imprimee 43)
A1451: 27 | B1451: WAFA ASSURANCE VIE CAMEROUN | C1451: CAMEROUN | D1451: Vie | E1451: Emissions | F1451: Individuelles | G1451: Titre de capitalisation | H1451: Emissions nettes | I1451: 2023 | J1451: 2987998 | K1451: PDF p. 48 (page imprimee 43)
A1452: 27 | B1452: WAFA ASSURANCE VIE CAMEROUN | C1452: CAMEROUN | D1452: Vie | E1452: Emissions | F1452: Individuelles | G1452: Complémentaires | H1452: Emissions nettes | I1452: 2022 | K1452: PDF p. 48 (page imprimee 43)
A1453: 27 | B1453: WAFA ASSURANCE VIE CAMEROUN | C1453: CAMEROUN | D1453: Vie | E1453: Emissions | F1453: Individuelles | G1453: Complémentaires | H1453: Emissions nettes | I1453: 2023 | J1453: 0 | K1453: PDF p. 48 (page imprimee 43)
A1454: 27 | B1454: WAFA ASSURANCE VIE CAMEROUN | C1454: CAMEROUN | D1454: Vie | E1454: Emissions | F1454: Collectives | G1454: Contrat en cas de vie | H1454: Emissions nettes | I1454: 2022 | K1454: PDF p. 48 (page imprimee 43)
A1455: 27 | B1455: WAFA ASSURANCE VIE CAMEROUN | C1455: CAMEROUN | D1455: Vie | E1455: Emissions | F1455: Collectives | G1455: Contrat en cas de vie | H1455: Emissions nettes | I1455: 2023 | J1455: 19500 | K1455: PDF p. 48 (page imprimee 43)
A1456: 27 | B1456: WAFA ASSURANCE VIE CAMEROUN | C1456: CAMEROUN | D1456: Vie | E1456: Emissions | F1456: Collectives | G1456: Contrat en cas de décès | H1456: Emissions nettes | I1456: 2022 | K1456: PDF p. 48 (page imprimee 43)
A1457: 27 | B1457: WAFA ASSURANCE VIE CAMEROUN | C1457: CAMEROUN | D1457: Vie | E1457: Emissions | F1457: Collectives | G1457: Contrat en cas de décès | H1457: Emissions nettes | I1457: 2023 | K1457: PDF p. 48 (page imprimee 43)
A1458: 27 | B1458: WAFA ASSURANCE VIE CAMEROUN | C1458: CAMEROUN | D1458: Vie | E1458: Emissions | F1458: Collectives | G1458: Mixte | H1458: Emissions nettes | I1458: 2022 | K1458: PDF p. 48 (page imprimee 43)
A1459: 27 | B1459: WAFA ASSURANCE VIE CAMEROUN | C1459: CAMEROUN | D1459: Vie | E1459: Emissions | F1459: Collectives | G1459: Mixte | H1459: Emissions nettes | I1459: 2023 | K1459: PDF p. 48 (page imprimee 43)
A1460: 27 | B1460: WAFA ASSURANCE VIE CAMEROUN | C1460: CAMEROUN | D1460: Vie | E1460: Emissions | F1460: Collectives | G1460: Epargne | H1460: Emissions nettes | I1460: 2022 | K1460: PDF p. 48 (page imprimee 43)
A1461: 27 | B1461: WAFA ASSURANCE VIE CAMEROUN | C1461: CAMEROUN | D1461: Vie | E1461: Emissions | F1461: Collectives | G1461: Epargne | H1461: Emissions nettes | I1461: 2023 | K1461: PDF p. 48 (page imprimee 43)
A1462: 27 | B1462: WAFA ASSURANCE VIE CAMEROUN | C1462: CAMEROUN | D1462: Vie | E1462: Emissions | F1462: Collectives | G1462: Titre de capitalisation | H1462: Emissions nettes | I1462: 2022 | K1462: PDF p. 48 (page imprimee 43)
A1463: 27 | B1463: WAFA ASSURANCE VIE CAMEROUN | C1463: CAMEROUN | D1463: Vie | E1463: Emissions | F1463: Collectives | G1463: Titre de capitalisation | H1463: Emissions nettes | I1463: 2023 | K1463: PDF p. 48 (page imprimee 43)
A1464: 27 | B1464: WAFA ASSURANCE VIE CAMEROUN | C1464: CAMEROUN | D1464: Vie | E1464: Emissions | F1464: Collectives | G1464: Complémentaires | H1464: Emissions nettes | I1464: 2022 | K1464: PDF p. 48 (page imprimee 43)
A1465: 27 | B1465: WAFA ASSURANCE VIE CAMEROUN | C1465: CAMEROUN | D1465: Vie | E1465: Emissions | F1465: Collectives | G1465: Complémentaires | H1465: Emissions nettes | I1465: 2023 | K1465: PDF p. 48 (page imprimee 43)
A1466: 27 | B1466: WAFA ASSURANCE VIE CAMEROUN | C1466: CAMEROUN | D1466: Vie | E1466: Emissions | F1466: Acceptations | G1466: Acceptations | H1466: Emissions nettes | I1466: 2022 | K1466: PDF p. 48 (page imprimee 43)
A1467: 27 | B1467: WAFA ASSURANCE VIE CAMEROUN | C1467: CAMEROUN | D1467: Vie | E1467: Emissions | F1467: Acceptations | G1467: Acceptations | H1467: Emissions nettes | I1467: 2023 | J1467: 0 | K1467: PDF p. 48 (page imprimee 43)
A1468: 27 | B1468: WAFA ASSURANCE VIE CAMEROUN | C1468: CAMEROUN | D1468: Vie | E1468: Prestations | F1468: Individuelles | G1468: Contrats en cas de vie | H1468: Prestations versees | I1468: 2022 | K1468: PDF p. 48 (page imprimee 43)
A1469: 27 | B1469: WAFA ASSURANCE VIE CAMEROUN | C1469: CAMEROUN | D1469: Vie | E1469: Prestations | F1469: Individuelles | G1469: Contrats en cas de vie | H1469: Prestations versees | I1469: 2023 | J1469: 0 | K1469: PDF p. 48 (page imprimee 43)
A1470: 27 | B1470: WAFA ASSURANCE VIE CAMEROUN | C1470: CAMEROUN | D1470: Vie | E1470: Prestations | F1470: Individuelles | G1470: Contrat en cas de décès | H1470: Prestations versees | I1470: 2022 | K1470: PDF p. 48 (page imprimee 43)
A1471: 27 | B1471: WAFA ASSURANCE VIE CAMEROUN | C1471: CAMEROUN | D1471: Vie | E1471: Prestations | F1471: Individuelles | G1471: Contrat en cas de décès | H1471: Prestations versees | I1471: 2023 | J1471: 470314 | K1471: PDF p. 48 (page imprimee 43)
A1472: 27 | B1472: WAFA ASSURANCE VIE CAMEROUN | C1472: CAMEROUN | D1472: Vie | E1472: Prestations | F1472: Individuelles | G1472: Mixte | H1472: Prestations versees | I1472: 2022 | K1472: PDF p. 48 (page imprimee 43)
A1473: 27 | B1473: WAFA ASSURANCE VIE CAMEROUN | C1473: CAMEROUN | D1473: Vie | E1473: Prestations | F1473: Individuelles | G1473: Mixte | H1473: Prestations versees | I1473: 2023 | J1473: 12294 | K1473: PDF p. 48 (page imprimee 43)
A1474: 27 | B1474: WAFA ASSURANCE VIE CAMEROUN | C1474: CAMEROUN | D1474: Vie | E1474: Prestations | F1474: Individuelles | G1474: Epargne | H1474: Prestations versees | I1474: 2022 | K1474: PDF p. 48 (page imprimee 43)
A1475: 27 | B1475: WAFA ASSURANCE VIE CAMEROUN | C1475: CAMEROUN | D1475: Vie | E1475: Prestations | F1475: Individuelles | G1475: Epargne | H1475: Prestations versees | I1475: 2023 | J1475: 1638903 | K1475: PDF p. 48 (page imprimee 43)
A1476: 27 | B1476: WAFA ASSURANCE VIE CAMEROUN | C1476: CAMEROUN | D1476: Vie | E1476: Prestations | F1476: Individuelles | G1476: Titre de capitalisation | H1476: Prestations versees | I1476: 2022 | K1476: PDF p. 48 (page imprimee 43)
A1477: 27 | B1477: WAFA ASSURANCE VIE CAMEROUN | C1477: CAMEROUN | D1477: Vie | E1477: Prestations | F1477: Individuelles | G1477: Titre de capitalisation | H1477: Prestations versees | I1477: 2023 | J1477: 1232378 | K1477: PDF p. 48 (page imprimee 43)
A1478: 27 | B1478: WAFA ASSURANCE VIE CAMEROUN | C1478: CAMEROUN | D1478: Vie | E1478: Prestations | F1478: Individuelles | G1478: Complémentaires | H1478: Prestations versees | I1478: 2022 | K1478: PDF p. 48 (page imprimee 43)
A1479: 27 | B1479: WAFA ASSURANCE VIE CAMEROUN | C1479: CAMEROUN | D1479: Vie | E1479: Prestations | F1479: Individuelles | G1479: Complémentaires | H1479: Prestations versees | I1479: 2023 | J1479: 0 | K1479: PDF p. 48 (page imprimee 43)
A1480: 27 | B1480: WAFA ASSURANCE VIE CAMEROUN | C1480: CAMEROUN | D1480: Vie | E1480: Prestations | F1480: Collectives | G1480: Contrat en cas de vie | H1480: Prestations versees | I1480: 2022 | K1480: PDF p. 48 (page imprimee 43)
A1481: 27 | B1481: WAFA ASSURANCE VIE CAMEROUN | C1481: CAMEROUN | D1481: Vie | E1481: Prestations | F1481: Collectives | G1481: Contrat en cas de vie | H1481: Prestations versees | I1481: 2023 | K1481: PDF p. 48 (page imprimee 43)
A1482: 27 | B1482: WAFA ASSURANCE VIE CAMEROUN | C1482: CAMEROUN | D1482: Vie | E1482: Prestations | F1482: Collectives | G1482: Contrat en cas de décès | H1482: Prestations versees | I1482: 2022 | K1482: PDF p. 48 (page imprimee 43)
A1483: 27 | B1483: WAFA ASSURANCE VIE CAMEROUN | C1483: CAMEROUN | D1483: Vie | E1483: Prestations | F1483: Collectives | G1483: Contrat en cas de décès | H1483: Prestations versees | I1483: 2023 | K1483: PDF p. 48 (page imprimee 43)
A1484: 27 | B1484: WAFA ASSURANCE VIE CAMEROUN | C1484: CAMEROUN | D1484: Vie | E1484: Prestations | F1484: Collectives | G1484: Mixte | H1484: Prestations versees | I1484: 2022 | K1484: PDF p. 48 (page imprimee 43)
A1485: 27 | B1485: WAFA ASSURANCE VIE CAMEROUN | C1485: CAMEROUN | D1485: Vie | E1485: Prestations | F1485: Collectives | G1485: Mixte | H1485: Prestations versees | I1485: 2023 | K1485: PDF p. 48 (page imprimee 43)
A1486: 27 | B1486: WAFA ASSURANCE VIE CAMEROUN | C1486: CAMEROUN | D1486: Vie | E1486: Prestations | F1486: Collectives | G1486: Epargne | H1486: Prestations versees | I1486: 2022 | K1486: PDF p. 48 (page imprimee 43)
A1487: 27 | B1487: WAFA ASSURANCE VIE CAMEROUN | C1487: CAMEROUN | D1487: Vie | E1487: Prestations | F1487: Collectives | G1487: Epargne | H1487: Prestations versees | I1487: 2023 | K1487: PDF p. 48 (page imprimee 43)
A1488: 27 | B1488: WAFA ASSURANCE VIE CAMEROUN | C1488: CAMEROUN | D1488: Vie | E1488: Prestations | F1488: Collectives | G1488: Titre de capitalisation | H1488: Prestations versees | I1488: 2022 | K1488: PDF p. 48 (page imprimee 43)
A1489: 27 | B1489: WAFA ASSURANCE VIE CAMEROUN | C1489: CAMEROUN | D1489: Vie | E1489: Prestations | F1489: Collectives | G1489: Titre de capitalisation | H1489: Prestations versees | I1489: 2023 | K1489: PDF p. 48 (page imprimee 43)
A1490: 27 | B1490: WAFA ASSURANCE VIE CAMEROUN | C1490: CAMEROUN | D1490: Vie | E1490: Prestations | F1490: Collectives | G1490: Complémentaires | H1490: Prestations versees | I1490: 2022 | K1490: PDF p. 48 (page imprimee 43)
A1491: 27 | B1491: WAFA ASSURANCE VIE CAMEROUN | C1491: CAMEROUN | D1491: Vie | E1491: Prestations | F1491: Collectives | G1491: Complémentaires | H1491: Prestations versees | I1491: 2023 | K1491: PDF p. 48 (page imprimee 43)
A1492: 27 | B1492: WAFA ASSURANCE VIE CAMEROUN | C1492: CAMEROUN | D1492: Vie | E1492: Prestations | F1492: Acceptations | G1492: Acceptations | H1492: Prestations versees | I1492: 2022 | K1492: PDF p. 48 (page imprimee 43)
A1493: 27 | B1493: WAFA ASSURANCE VIE CAMEROUN | C1493: CAMEROUN | D1493: Vie | E1493: Prestations | F1493: Acceptations | G1493: Acceptations | H1493: Prestations versees | I1493: 2023 | J1493: 0 | K1493: PDF p. 48 (page imprimee 43)
A1494: 28 | B1494: ASSURANCES & REASSURANCES AFRICAINES SA | C1494: CAMEROUN | D1494: Non-vie | E1494: Emissions | F1494: Affaires directes | G1494: Accidents corporels et maladie | H1494: Primes émises | I1494: 2022 | J1494: 531934 | K1494: PDF p. 50 (page imprimee 45)
A1495: 28 | B1495: ASSURANCES & REASSURANCES AFRICAINES SA | C1495: CAMEROUN | D1495: Non-vie | E1495: Emissions | F1495: Affaires directes | G1495: Accidents corporels et maladie | H1495: Primes acquises (PA) | I1495: 2022 | J1495: 1526414 | K1495: PDF p. 50 (page imprimee 45)
A1496: 28 | B1496: ASSURANCES & REASSURANCES AFRICAINES SA | C1496: CAMEROUN | D1496: Non-vie | E1496: Emissions | F1496: Affaires directes | G1496: Accidents corporels et maladie | H1496: Primes émises | I1496: 2023 | J1496: 2544855 | K1496: PDF p. 50 (page imprimee 45)
A1497: 28 | B1497: ASSURANCES & REASSURANCES AFRICAINES SA | C1497: CAMEROUN | D1497: Non-vie | E1497: Emissions | F1497: Affaires directes | G1497: Accidents corporels et maladie | H1497: Primes acquises (PA) | I1497: 2023 | J1497: 2520585 | K1497: PDF p. 50 (page imprimee 45)
A1498: 28 | B1498: ASSURANCES & REASSURANCES AFRICAINES SA | C1498: CAMEROUN | D1498: Non-vie | E1498: Emissions | F1498: Affaires directes | G1498: Automobile : Responsabilité Civile | H1498: Primes émises | I1498: 2022 | J1498: 1532344 | K1498: PDF p. 50 (page imprimee 45)
A1499: 28 | B1499: ASSURANCES & REASSURANCES AFRICAINES SA | C1499: CAMEROUN | D1499: Non-vie | E1499: Emissions | F1499: Affaires directes | G1499: Automobile : Responsabilité Civile | H1499: Primes acquises (PA) | I1499: 2022 | J1499: 1482151 | K1499: PDF p. 50 (page imprimee 45)
...

Sheet Chiffres clés (brut)
A1: No enregistrement | B1: Societe | C1: Pays | D1: Branche | E1: Rubrique | F1: Annee | G1: Valeur (milliers F CFA) | H1: Cellule source
A2: 1 | B2: ATLANTIQUE ASSURANCE BENIN VIE | C2: BENIN | D2: Vie | E2: Produits financiers nets | F2: 2022 | G2: 280781 | H2: PDF p. 15 (page imprimee 10)
A3: 1 | B3: ATLANTIQUE ASSURANCE BENIN VIE | C3: BENIN | D3: Vie | E3: Produits financiers nets | F3: 2023 | G3: 263564 | H3: PDF p. 15 (page imprimee 10)
A4: 1 | B4: ATLANTIQUE ASSURANCE BENIN VIE | C4: BENIN | D4: Vie | E4: Commissions | F4: 2022 | G4: 203777 | H4: PDF p. 15 (page imprimee 10)
A5: 1 | B5: ATLANTIQUE ASSURANCE BENIN VIE | C5: BENIN | D5: Vie | E5: Commissions | F5: 2023 | G5: 322156 | H5: PDF p. 15 (page imprimee 10)
A6: 1 | B6: ATLANTIQUE ASSURANCE BENIN VIE | C6: BENIN | D6: Vie | E6: Autres charges de l'exercice | F6: 2022 | G6: 1155007 | H6: PDF p. 15 (page imprimee 10)
A7: 1 | B7: ATLANTIQUE ASSURANCE BENIN VIE | C7: BENIN | D7: Vie | E7: Autres charges de l'exercice | F7: 2023 | G7: 1547992 | H7: PDF p. 15 (page imprimee 10)
A8: 1 | B8: ATLANTIQUE ASSURANCE BENIN VIE | C8: BENIN | D8: Vie | E8: Provisions mathématiques (clôture) | F8: 2022 | G8: 6983688 | H8: PDF p. 15 (page imprimee 10)
A9: 1 | B9: ATLANTIQUE ASSURANCE BENIN VIE | C9: BENIN | D9: Vie | E9: Provisions mathématiques (clôture) | F9: 2023 | G9: 7529625 | H9: PDF p. 15 (page imprimee 10)
A10: 1 | B10: ATLANTIQUE ASSURANCE BENIN VIE | C10: BENIN | D10: Vie | E10: Provisions mathématiques (ouverture) | F10: 2022 | G10: 6015491 | H10: PDF p. 15 (page imprimee 10)
A11: 1 | B11: ATLANTIQUE ASSURANCE BENIN VIE | C11: BENIN | D11: Vie | E11: Provisions mathématiques (ouverture) | F11: 2023 | G11: 6983688 | H11: PDF p. 15 (page imprimee 10)
A12: 1 | B12: ATLANTIQUE ASSURANCE BENIN VIE | C12: BENIN | D12: Vie | E12: Primes cédées aux réassureurs | F12: 2022 | G12: 48176 | H12: PDF p. 15 (page imprimee 10)
A13: 1 | B13: ATLANTIQUE ASSURANCE BENIN VIE | C13: BENIN | D13: Vie | E13: Primes cédées aux réassureurs | F13: 2023 | G13: 40020 | H13: PDF p. 15 (page imprimee 10)
... A773: 26 | B773: SUNU ASSURANCES VIE CAMEROUN | C773: CAMEROUN | D773: Vie | E773: Dont liquidités | F773: 2023 | G773: 24893707 | H773: PDF p. 47 (page imprimee 42)
A774: 27 | B774: WAFA ASSURANCE VIE CAMEROUN | C774: CAMEROUN | D774: Vie | E774: Produits financiers nets | F774: 2022 | H774: PDF p. 48 (page imprimee 43)
A775: 27 | B775: WAFA ASSURANCE VIE CAMEROUN | C775: CAMEROUN | D775: Vie | E775: Produits financiers nets | F775: 2023 | G775: 1121847 | H775: PDF p. 48 (page imprimee 43)
A776: 27 | B776: WAFA ASSURANCE VIE CAMEROUN | C776: CAMEROUN | D776: Vie | E776: Commissions | F776: 2022 | H776: PDF p. 48 (page imprimee 43)
A777: 27 | B777: WAFA ASSURANCE VIE CAMEROUN | C777: CAMEROUN | D777: Vie | E777: Commissions | F777: 2023 | G777: 516396 | H777: PDF p. 48 (page imprimee 43)
A778: 27 | B778: WAFA ASSURANCE VIE CAMEROUN | C778: CAMEROUN | D778: Vie | E778: Autres charges de l'exercice | F778: 2022 | H778: PDF p. 48 (page imprimee 43)
A779: 27 | B779: WAFA ASSURANCE VIE CAMEROUN | C779: CAMEROUN | D779: Vie | E779: Autres charges de l'exercice | F779: 2023 | G779: 1377252 | H779: PDF p. 48 (page imprimee 43)
A780: 27 | B780: WAFA ASSURANCE VIE CAMEROUN | C780: CAMEROUN | D780: Vie | E780: Provisions mathématiques (clôture) | F780: 2022 | H780: PDF p. 48 (page imprimee 43)
A781: 27 | B781: WAFA ASSURANCE VIE CAMEROUN | C781: CAMEROUN | D781: Vie | E781: Provisions mathématiques (clôture) | F781: 2023 | G781: 20405099 | H781: PDF p. 48 (page imprimee 43)
A782: 27 | B782: WAFA ASSURANCE VIE CAMEROUN | C782: CAMEROUN | D782: Vie | E782: Provisions mathématiques (ouverture) | F782: 2022 | H782: PDF p. 48 (page imprimee 43)
A783: 27 | B783: WAFA ASSURANCE VIE CAMEROUN | C783: CAMEROUN | D783: Vie | E783: Provisions mathématiques (ouverture) | F783: 2023 | G783: 20405099 | H783: PDF p. 48 (page imprimee 43)
A784: 27 | B784: WAFA ASSURANCE VIE CAMEROUN | C784: CAMEROUN | D784: Vie | E784: Primes cédées aux réassureurs | F784: 2022 | H784: PDF p. 48 (page imprimee 43)
A785: 27 | B785: WAFA ASSURANCE VIE CAMEROUN | C785: CAMEROUN | D785: Vie | E785: Primes cédées aux réassureurs | F785: 2023 | G785: 96485 | H785: PDF p. 48 (page imprimee 43)
A786: 27 | B786: WAFA ASSURANCE VIE CAMEROUN | C786: CAMEROUN | D786: Vie | E786: Part des réassureurs dans les charges | F786: 2022 | H786: PDF p. 48 (page imprimee 43)
A787: 27 | B787: WAFA ASSURANCE VIE CAMEROUN | C787: CAMEROUN | D787: Vie | E787: Part des réassureurs dans les charges | F787: 2023 | G787: 9234 | H787: PDF p. 48 (page imprimee 43)
A788: 27 | B788: WAFA ASSURANCE VIE CAMEROUN | C788: CAMEROUN | D788: Vie | E788: Résultats d’exploitations nets | F788: 2022 | H788: PDF p. 48 (page imprimee 43)
A789: 27 | B789: WAFA ASSURANCE VIE CAMEROUN | C789: CAMEROUN | D789: Vie | E789: Résultats d’exploitations nets | F789: 2023 | G789: 358425 | H789: PDF p. 48 (page imprimee 43)
A790: 27 | B790: WAFA ASSURANCE VIE CAMEROUN | C790: CAMEROUN | D790: Vie | E790: Total des capitaux propres et réserves | F790: 2022 | H790: PDF p. 48 (page imprimee 43)
A791: 27 | B791: WAFA ASSURANCE VIE CAMEROUN | C791: CAMEROUN | D791: Vie | E791: Total des capitaux propres et réserves | F791: 2023 | G791: 5134551 | H791: PDF p. 48 (page imprimee 43)
A792: 27 | B792: WAFA ASSURANCE VIE CAMEROUN | C792: CAMEROUN | D792: Vie | E792: Marge réglementaire | F792: 2022 | H792: PDF p. 48 (page imprimee 43)
A793: 27 | B793: WAFA ASSURANCE VIE CAMEROUN | C793: CAMEROUN | D793: Vie | E793: Marge réglementaire | F793: 2023 | G793: 939760 | H793: PDF p. 48 (page imprimee 43)
A794: 27 | B794: WAFA ASSURANCE VIE CAMEROUN | C794: CAMEROUN | D794: Vie | E794: Marge disponible | F794: 2022 | H794: PDF p. 48 (page imprimee 43)
A795: 27 | B795: WAFA ASSURANCE VIE CAMEROUN | C795: CAMEROUN | D795: Vie | E795: Marge disponible | F795: 2023 | G795: 5322708 | H795: PDF p. 48 (page imprimee 43)
A796: 27 | B796: WAFA ASSURANCE VIE CAMEROUN | C796: CAMEROUN | D796: Vie | E796: Engagements Réglementés | F796: 2022 | H796: PDF p. 48 (page imprimee 43)
A797: 27 | B797: WAFA ASSURANCE VIE CAMEROUN | C797: CAMEROUN | D797: Vie | E797: Engagements Réglementés | F797: 2023 | G797: 20894700 | H797: PDF p. 48 (page imprimee 43)
A798: 27 | B798: WAFA ASSURANCE VIE CAMEROUN | C798: CAMEROUN | D798: Vie | E798: Actifs admis | F798: 2022 | H798: PDF p. 48 (page imprimee 43)
A799: 27 | B799: WAFA ASSURANCE VIE CAMEROUN | C799: CAMEROUN | D799: Vie | E799: Actifs admis | F799: 2023 | G799: 24666274 | H799: PDF p. 48 (page imprimee 43)
A800: 27 | B800: WAFA ASSURANCE VIE CAMEROUN | C800: CAMEROUN | D800: Vie | E800: Dont liquidités | F800: 2022 | H800: PDF p. 48 (page imprimee 43)
A801: 27 | B801: WAFA ASSURANCE VIE CAMEROUN | C801: CAMEROUN | D801: Vie | E801: Dont liquidités | F801: 2023 | G801: 8322124 | H801: PDF p. 48 (page imprimee 43)
A802: 28 | B802: ASSURANCES & REASSURANCES AFRICAINES SA | C802: CAMEROUN | D802: Non-vie | E802: Produits financiers nets | F802: 2022 | G802: 178501 | H802: PDF p. 50 (page imprimee 45)
A803: 28 | B803: ASSURANCES & REASSURANCES AFRICAINES SA | C803: CAMEROUN | D803: Non-vie | E803: Produits financiers nets | F803: 2023 | G803: 159970 | H803: PDF p. 50 (page imprimee 45)
A804: 28 | B804: ASSURANCES & REASSURANCES AFRICAINES SA | C804: CAMEROUN | D804: Non-vie | E804: Commissions | F804: 2022 | G804: 471525 | H804: PDF p. 50 (page imprimee 45)
A805: 28 | B805: ASSURANCES & REASSURANCES AFRICAINES SA | C805: CAMEROUN | D805: Non-vie | E805: Commissions | F805: 2023 | G805: 1095225 | H805: PDF p. 50 (page imprimee 45)
A806: 28 | B806: ASSURANCES & REASSURANCES AFRICAINES SA | C806: CAMEROUN | D806: Non-vie | E806: Autres charges de l'exercice | F806: 2022 | G806: 1829851 | H806: PDF p. 50 (page imprimee 45)
A807: 28 | B807: ASSURANCES & REASSURANCES AFRICAINES SA | C807: CAMEROUN | D807: Non-vie | E807: Autres charges de l'exercice | F807: 2023 | G807: 2044156 | H807: PDF p. 50 (page imprimee 45)
A808: 28 | B808: ASSURANCES & REASSURANCES AFRICAINES SA | C808: CAMEROUN | D808: Non-vie | E808: Provisions pour risques en cours | F808: 2022 | G808: 1391941 | H808: PDF p. 50 (page imprimee 45)
A809: 28 | B809: ASSURANCES & REASSURANCES AFRICAINES SA | C809: CAMEROUN | D809: Non-vie | E809: Provisions pour risques en cours | F809: 2023 | G809: 1195486 | H809: PDF p. 50 (page imprimee 45)
A810: 28 | B810: ASSURANCES & REASSURANCES AFRICAINES SA | C810: CAMEROUN | D810: Non-vie | E810: Primes cédées aux réassureurs | F810: 2022 | G810: 754075 | H810: PDF p. 50 (page imprimee 45)
A811: 28 | B811: ASSURANCES & REASSURANCES AFRICAINES SA | C811: CAMEROUN | D811: Non-vie | E811: Primes cédées aux réassureurs | F811: 2023 | G811: 538721 | H811: PDF p. 50 (page imprimee 45)
A812: 28 | B812: ASSURANCES & REASSURANCES AFRICAINES SA | C812: CAMEROUN | D812: Non-vie | E812: Primes acquises aux réassureurs | F812: 2022 | G812: 753761 | H812: PDF p. 50 (page imprimee 45)
... A1117: 37 | B1117: ASSURANCES GENERALES DU CONGO (AGC) | C1117: CONGO BRAZZAVILLE | D1117: Non-vie | E1117: Dont liquidités | F1117: 2023 | G1117: 2577828 | H1117: PDF p. 64 (page imprimee 59)
A1118: 38 | B1118: AMC CONGO Brazzaville | C1118: CONGO BRAZZAVILLE | D1118: Non-vie | E1118: Produits financiers nets | F1118: 2022 | H1118: PDF p. 65 (page imprimee 60)
A1119: 38 | B1119: AMC CONGO Brazzaville | C1119: CONGO BRAZZAVILLE | D1119: Non-vie | E1119: Produits financiers nets | F1119: 2023 | G1119: 212067 | H1119: PDF p. 65 (page imprimee 60)
A1120: 38 | B1120: AMC CONGO Brazzaville | C1120: CONGO BRAZZAVILLE | D1120: Non-vie | E1120: Commissions | F1120: 2022 | H1120: PDF p. 65 (page imprimee 60)
A1121: 38 | B1121: AMC CONGO Brazzaville | C1121: CONGO BRAZZAVILLE | D1121: Non-vie | E1121: Commissions | F1121: 2023 | G1121: 644154 | H1121: PDF p. 65 (page imprimee 60)
A1122: 38 | B1122: AMC CONGO Brazzaville | C1122: CONGO BRAZZAVILLE | D1122: Non-vie | E1122: Autres charges de l'exercice | F1122: 2022 | H1122: PDF p. 65 (page imprimee 60)
A1123: 38 | B1123: AMC CONGO Brazzaville | C1123: CONGO BRAZZAVILLE | D1123: Non-vie | E1123: Autres charges de l'exercice | F1123: 2023 | G1123: 1773984 | H1123: PDF p. 65 (page imprimee 60)
A1124: 38 | B1124: AMC CONGO Brazzaville | C1124: CONGO BRAZZAVILLE | D1124: Non-vie | E1124: Provisions pour risques en cours | F1124: 2022 | H1124: PDF p. 65 (page imprimee 60)
A1125: 38 | B1125: AMC CONGO Brazzaville | C1125: CONGO BRAZZAVILLE | D1125: Non-vie | E1125: Provisions pour risques en cours | F1125: 2023 | G1125: 484774 | H1125: PDF p. 65 (page imprimee 60)
A1126: 38 | B1126: AMC CONGO Brazzaville | C1126: CONGO BRAZZAVILLE | D1126: Non-vie | E1126: Primes cédées aux réassureurs | F1126: 2022 | H1126: PDF p. 65 (page imprimee 60)
A1127: 38 | B1127: AMC CONGO Brazzaville | C1127: CONGO BRAZZAVILLE | D1127: Non-vie | E1127: Primes cédées aux réassureurs | F1127: 2023 | G1127: 630902 | H1127: PDF p. 65 (page imprimee 60)
A1128: 38 | B1128: AMC CONGO Brazzaville | C1128: CONGO BRAZZAVILLE | D1128: Non-vie | E1128: Primes acquises aux réassureurs | F1128: 2022 | H1128: PDF p. 65 (page imprimee 60)
A1129: 38 | B1129: AMC CONGO Brazzaville | C1129: CONGO BRAZZAVILLE | D1129: Non-vie | E1129: Primes acquises aux réassureurs | F1129: 2023 | G1129: 446394 | H1129: PDF p. 65 (page imprimee 60)
A1130: 38 | B1130: AMC CONGO Brazzaville | C1130: CONGO BRAZZAVILLE | D1130: Non-vie | E1130: Part des réassureurs dans les charges | F1130: 2022 | H1130: PDF p. 65 (page imprimee 60)
A1131: 38 | B1131: AMC CONGO Brazzaville | C1131: CONGO BRAZZAVILLE | D1131: Non-vie | E1131: Part des réassureurs dans les charges | F1131: 2023 | G1131: 177561 | H1131: PDF p. 65 (page imprimee 60)
A1132: 38 | B1132: AMC CONGO Brazzaville | C1132: CONGO BRAZZAVILLE | D1132: Non-vie | E1132: Prestations et frais payés | F1132: 2022 | H1132: PDF p. 65 (page imprimee 60)
A1133: 38 | B1133: AMC CONGO Brazzaville | C1133: CONGO BRAZZAVILLE | D1133: Non-vie | E1133: Prestations et frais payés | F1133: 2023 | G1133: 453464 | H1133: PDF p. 65 (page imprimee 60)
A1134: 38 | B1134: AMC CONGO Brazzaville | C1134: CONGO BRAZZAVILLE | D1134: Non-vie | E1134: Provisions pour sinistres à payer | F1134: 2022 | H1134: PDF p. 65 (page imprimee 60)
A1135: 38 | B1135: AMC CONGO Brazzaville | C1135: CONGO BRAZZAVILLE | D1135: Non-vie | E1135: Provisions pour sinistres à payer | F1135: 2023 | G1135: 568332 | H1135: PDF p. 65 (page imprimee 60)
A1136: 38 | B1136: AMC CONGO Brazzaville | C1136: CONGO BRAZZAVILLE | D1136: Non-vie | E1136: Résultats d’exploitations nets | F1136: 2022 | H1136: PDF p. 65 (page imprimee 60)
A1137: 38 | B1137: AMC CONGO Brazzaville | C1137: CONGO BRAZZAVILLE | D1137: Non-vie | E1137: Résultats d’exploitations nets | F1137: 2023 | G1137: -728949 | H1137: PDF p. 65 (page imprimee 60)
A1138: 38 | B1138: AMC CONGO Brazzaville | C1138: CONGO BRAZZAVILLE | D1138: Non-vie | E1138: Total des capitaux propres et réserves | F1138: 2022 | H1138: PDF p. 65 (page imprimee 60)
A1139: 38 | B1139: AMC CONGO Brazzaville | C1139: CONGO BRAZZAVILLE | D1139: Non-vie | E1139: Total des capitaux propres et réserves | F1139: 2023 | G1139: 5000000 | H1139: PDF p. 65 (page imprimee 60)
A1140: 38 | B1140: AMC CONGO Brazzaville | C1140: CONGO BRAZZAVILLE | D1140: Non-vie | E1140: Marge réglementaire | F1140: 2022 | H1140: PDF p. 65 (page imprimee 60)
A1141: 38 | B1141: AMC CONGO Brazzaville | C1141: CONGO BRAZZAVILLE | D1141: Non-vie | E1141: Marge réglementaire | F1141: 2023 | G1141: 637551 | H1141: PDF p. 65 (page imprimee 60)
A1142: 38 | B1142: AMC CONGO Brazzaville | C1142: CONGO BRAZZAVILLE | D1142: Non-vie | E1142: Marge disponible | F1142: 2022 | H1142: PDF p. 65 (page imprimee 60)
A1143: 38 | B1143: AMC CONGO Brazzaville | C1143: CONGO BRAZZAVILLE | D1143: Non-vie | E1143: Marge disponible | F1143: 2023 | G1143: 3481583 | H1143: PDF p. 65 (page imprimee 60)
A1144: 38 | B1144: AMC CONGO Brazzaville | C1144: CONGO BRAZZAVILLE | D1144: Non-vie | E1144: Engagements Réglementés | F1144: 2022 | H1144: PDF p. 65 (page imprimee 60)
A1145: 38 | B1145: AMC CONGO Brazzaville | C1145: CONGO BRAZZAVILLE | D1145: Non-vie | E1145: Engagements Réglementés | F1145: 2023 | G1145: 1215472 | H1145: PDF p. 65 (page imprimee 60)
A1146: 38 | B1146: AMC CONGO Brazzaville | C1146: CONGO BRAZZAVILLE | D1146: Non-vie | E1146: Actifs admis | F1146: 2022 | H1146: PDF p. 65 (page imprimee 60)
A1147: 38 | B1147: AMC CONGO Brazzaville | C1147: CONGO BRAZZAVILLE | D1147: Non-vie | E1147: Actifs admis | F1147: 2023 | G1147: 4391683 | H1147: PDF p. 65 (page imprimee 60)
A1148: 38 | B1148: AMC CONGO Brazzaville | C1148: CONGO BRAZZAVILLE | D1148: Non-vie | E1148: Dont liquidités | F1148: 2022 | H1148: PDF p. 65 (page imprimee 60)
A1149: 38 | B1149: AMC CONGO Brazzaville | C1149: CONGO BRAZZAVILLE | D1149: Non-vie | E1149: Dont liquidités | F1149: 2023 | G1149: 4047898 | H1149: PDF p. 65 (page imprimee 60)
A1150: 39 | B1150: NOUVELLE SOCIETE INTERAFRICAINE D'ASSURANCES | C1150: CONGO BRAZZAVILLE | D1150: Non-vie | E1150: Produits financiers nets | F1150: 2022 | G1150: 146271 | H1150: PDF p. 66 (page imprimee 61)
A1151: 39 | B1151: NOUVELLE SOCIETE INTERAFRICAINE D'ASSURANCES | C1151: CONGO BRAZZAVILLE | D1151: Non-vie | E1151: Produits financiers nets | F1151: 2023 | G1151: 576195 | H1151: PDF p. 66 (page imprimee 61)
A1152: 39 | B1152: NOUVELLE SOCIETE INTERAFRICAINE D'ASSURANCES | C1152: CONGO BRAZZAVILLE | D1152: Non-vie | E1152: Commissions | F1152: 2022 | G1152: 1073416 | H1152: PDF p. 66 (page imprimee 61)
A1153: 39 | B1153: NOUVELLE SOCIETE INTERAFRICAINE D'ASSURANCES | C1153: CONGO BRAZZAVILLE | D1153: Non-vie | E1153: Commissions | F1153: 2023 | G1153: 1682812 | H1153: PDF p. 66 (page imprimee 61)
A1154: 39 | B1154: NOUVELLE SOCIETE INTERAFRICAINE D'ASSURANCES | C1154: CONGO BRAZZAVILLE | D1154: Non-vie | E1154: Autres charges de l'exercice | F1154: 2022 | G1154: 2698012 | H1154: PDF p. 66 (page imprimee 61)
A1155: 39 | B1155: NOUVELLE SOCIETE INTERAFRICAINE D'ASSURANCES | C1155: CONGO BRAZZAVILLE | D1155: Non-vie | E1155: Autres charges de l'exercice | F1155: 2023 | G1155: 3628457 | H1155: PDF p. 66 (page imprimee 61)
A1156: 39 | B1156: NOUVELLE SOCIETE INTERAFRICAINE D'ASSURANCES | C1156: CONGO BRAZZAVILLE | D1156: Non-vie | E1156: Provisions pour risques en cours | F1156: 2022 | G1156: 1360815 | H1156: PDF p. 66 (page imprimee 61)
A1157: 39 | B1157: NOUVELLE SOCIETE INTERAFRICAINE D'ASSURANCES | C1157: CONGO BRAZZAVILLE | D1157: Non-vie | E1157: Provisions pour risques en cours | F1157: 2023 | G1157: 1956897 | H1157: PDF p. 66 (page imprimee 61)
A1158: 39 | B1158: NOUVELLE SOCIETE INTERAFRICAINE D'ASSURANCES | C1158: CONGO BRAZZAVILLE | D1158: Non-vie | E1158: Primes cédées aux réassureurs | F1158: 2022 | G1158: 1163643 | H1158: PDF p. 66 (page imprimee 61)
A1159: 39 | B1159: NOUVELLE SOCIETE INTERAFRICAINE D'ASSURANCES | C1159: CONGO BRAZZAVILLE | D1159: Non-vie | E1159: Primes cédées aux réassureurs | F1159: 2023 | G1159: 2852118 | H1159: PDF p. 66 (page imprimee 61)
A1160: 39 | B1160: NOUVELLE SOCIETE INTERAFRICAINE D'ASSURANCES | C1160: CONGO BRAZZAVILLE | D1160: Non-vie | E1160: Primes acquises aux réassureurs | F1160: 2022 | G1160: 1214414 | H1160: PDF p. 66 (page imprimee 61)
... A1297: 43 | B1297: PRUDENTIAL BELIFE INSURANCE | C1297: COTE D'IVOIRE | D1297: Vie | E1297: Dont liquidités | F1297: 2023 | G1297: 13252969 | H1297: PDF p. 72 (page imprimee 67)
A1298: 44 | B1298: NSIA VIE CÔTE-D'IVOIRE | C1298: COTE D'IVOIRE | D1298: Vie | E1298: Produits financiers nets | F1298: 2022 | H1298: PDF p. 73 (page imprimee 68)
A1299: 44 | B1299: NSIA VIE CÔTE-D'IVOIRE | C1299: COTE D'IVOIRE | D1299: Vie | E1299: Produits financiers nets | F1299: 2023 | G1299: 2325279 | H1299: PDF p. 73 (page imprimee 68)
...
